Workbook

Sheet README
A1: Kenya as East Africa's low-carbon industry hub - strategy model
A3: Question: Should Kenya position itself as East Africa's hub for energy-intensive, low-carbon industry (data centres first), and what would it take?
A5: How to read this workbook
A6: Summary Headline outputs, all linked. Start here.
A7: Inputs Every assumption, tagged [S] sourced or [A] analyst assumption. Change blue cells; everything recalculates.
A8: Grid Peak demand versus firm, evening-capable supply, 2026-2032, in three supply cases (Stress / Base / Favourable).
A9: Hub Data-centre demand in three hub cases (Status quo / Targeted / Ambitious) and the size of the prize in 2030.
A10: Matrix Reserve margin, firm-MW gap and connectable load for every supply x hub combination.
A11: UnitEconomics Tenant cost per kW-month and an illustrative 44 MW campus (NPV, IRR, break-even fee, sensitivities).
A12: Levers Five levers sized against the 2030 firm-capacity gap, with indicative annual cost.
A13: Screen Judgement-based screen of which industries fit Kenya's evening-constrained grid.
A14: Sources Source register (S1-S27) and the conflicts between sources and how each is resolved.
... A24: 5. The campus case is pre-tax and unlevered and meant to show what price or cost of capital a campus needs, not to value a specific project.

Sheet Summary
A1: Summary of results - Kenya as East Africa's low-carbon industry hub
A2: All figures are live links to the calculation sheets. Scenario definitions are on the Inputs sheet.
A4: 1. Grid headroom (supply cases) | B4: Stress | C4: Base | D4: Favourable
A5: Peak demand, Jun 2026 (MW) | B5: =Grid!C5 -> 2514 | C5: =Grid!C20 -> 2514 | D5: =Grid!C35 -> 2514
A6: Firm available capacity, Jun 2026 (MW) | B6: =Grid!C14 -> 2476.29 | C6: =Grid!C29 -> 2597.9676 | D6: =Grid!C44 -> 3035.1522
A7: Spare MW, Jun 2026 | B7: =Grid!C16 -> -37.71 | C7: =Grid!C31 -> 83.9676 | D7: =Grid!C46 -> 521.1522 | E7: Base: the whole national spare margin
A8: Reserve margin 2027 (no hub) | B8: =Grid!D15 -> -0.087962963 | C8: =Grid!D30 -> 0.088353147 | D8: =Grid!D45 -> 0.2695201
A9: Reserve margin 2028 (no hub) | B9: =Grid!E15 -> -0.081859693 | C9: =Grid!E30 -> 0.021927838 | D9: =Grid!E45 -> 0.23803831
A10: Reserve margin 2030 (no hub) | B10: =Grid!G15 -> -0.18936499 | C10: =Grid!G30 -> -0.027799598 | D10: =Grid!G45 -> 0.2538366
A11: Reserve margin 2032 (no hub) | B11: =Grid!I15 -> -0.30501114 | C11: =Grid!I30 -> -0.061068377 | D11: =Grid!I45 -> 0.31536112
A12: New firm MW needed per year just to hold the margin, 2030 | B12: =Grid!G17 -> 253.35328 | C12: =Grid!G32 -> 197.39105 | D12: =Grid!G47 -> 145.51346
A14: 2. The prize (hub cases, 2030) | B14: Status quo | C14: Targeted hub | D14: Ambitious hub
A15: Kenya data-centre IT capacity (MW) | B15: =Hub!C26 -> 74 | C15: =Hub!D26 -> 222 | D15: =Hub!E26 -> 370
A16: Share of Africa capacity | B16: =Hub!C27 -> 0.04 | C16: =Hub!D27 -> 0.12 | D16: =Hub!E27 -> 0.2
A17: Infrastructure-fee revenue pool ($m/yr) | B17: =Hub!C28 -> 99.9 | C17: =Hub!D28 -> 299.7 | D17: =Hub!E28 -> 499.5
A18: Build investment 2026-2030 ($bn) | B18: =Hub!C29 -> 0.232 | C18: =Hub!D29 -> 1.416 | D18: =Hub!E29 -> 2.6
A19: Operational jobs | B19: =Hub!C31 -> 317.14286 | C19: =Hub!D31 -> 951.42857 | D19: =Hub!E31 -> 1585.7143
A20: Hub load added to grid (MW) | B20: =Hub!C32 -> 0 | C20: =Hub!D32 -> 155.4 | D20: =Hub!E32 -> 310.8
A21: Hub-attributable firming cost ($m/yr) | B21: =Hub!C34 -> 0 | C21: =Hub!D34 -> 29.348113 | D21: =Hub!E34 -> 58.696225
A22: Firming cost as % of fee revenue | B22: =Hub!C35 -> 0 | C22: =Hub!D35 -> 0.097924967 | D22: =Hub!E35 -> 0.11750996
A23: Energy drawn by the data-centre estate (TWh/yr) | B23: =Hub!C36 -> 0.680652 | C23: =Hub!D36 -> 2.041956 | D23: =Hub!E36 -> 3.40326
A25: 3. Reserve margin in 2030 (rows: supply case; columns: hub case) | B25: Status quo | C25: Targeted hub | D25: Ambitious hub
A26: Stress supply | B26: =Matrix!C16 -> -0.18936499 | C26: =Matrix!D16 -> -0.22459551 | D26: =Matrix!E16 -> -0.2568913
A27: Base supply | B27: =Matrix!C17 -> -0.027799598 | C27: =Matrix!D17 -> -0.072371523 | D27: =Matrix!E17 -> -0.11303568
A28: Favourable supply | B28: =Matrix!C18 -> 0.2538366 | C28: =Matrix!D18 -> 0.1931592 | D28: =Matrix!E18 -> 0.13808349
A30: 4. Firm MW needed in 2030 to reach the minimum reserve margin | B30: Status quo | C30: Targeted hub | D30: Ambitious hub
A31: Stress supply | B31: =Matrix!C21 -> 989.70617 | C31: =Matrix!D21 -> 1160.6462 | D31: =Matrix!E21 -> 1331.5862
A32: Base supply | B32: =Matrix!C22 -> 413.32645 | C32: =Matrix!D22 -> 584.26645 | D32: =Matrix!E22 -> 755.20645
A33: Favourable supply | B33: =Matrix!C23 -> 0 | C33: =Matrix!D23 -> 0 | D33: =Matrix!E23 -> 0
A35: 5. Firm MW needed in 2030 to reach the target reserve margin | B35: Status quo | C35: Targeted hub | D35: Ambitious hub
A36: Stress supply | B36: =Matrix!C26 -> 1160.7196 | C36: =Matrix!D26 -> 1339.4296 | D36: =Matrix!E26 -> 1518.1396
A37: Base supply | B37: =Matrix!C27 -> 575.03527 | C37: =Matrix!D27 -> 753.74527 | D37: =Matrix!E27 -> 932.45527
A38: Favourable supply | B38: =Matrix!C28 -> 0 | C38: =Matrix!D28 -> 0 | D38: =Matrix!E28 -> 40.117919
A40: 6. Connectable IT MW at the minimum reserve margin | B40: 2027 | C40: 2028 | D40: 2030
A41: Stress supply | B41: =Matrix!D36 -> 0 | C41: =Matrix!E36 -> 0 | D41: =Matrix!G36 -> 0
A42: Base supply | B42: =Matrix!D37 -> 0 | C42: =Matrix!E37 -> 0 | D42: =Matrix!G37 -> 0
A43: Favourable supply | B43: =Matrix!D38 -> 387.43048 | C43: =Matrix!E38 -> 331.25429 | D43: =Matrix!G38 -> 407.00538
A45: 7. Tenant cost per IT kW-month ($) | B45: Stress | C45: Base | D45: Favourable
A46: Infrastructure fee | B46: =UnitEconomics!C5 -> 110 | C46: =UnitEconomics!D5 -> 150 | D46: =UnitEconomics!E5 -> 200
A47: Grid power | B47: =UnitEconomics!C6 -> 112.42 | C47: =UnitEconomics!D6 -> 91.98 | D47: =UnitEconomics!E6 -> 66.43
A48: Evening self-supply premium | B48: =UnitEconomics!C7 -> 22.033118 | C48: =UnitEconomics!D7 -> 22.033118 | D48: =UnitEconomics!E7 -> 22.033118
A49: All-in cost | B49: =UnitEconomics!C8 -> 244.45312 | C49: =UnitEconomics!D8 -> 264.01312 | D49: =UnitEconomics!E8 -> 288.46312
A50: Power share of all-in cost | B50: =UnitEconomics!C9 -> 0.55001597 | C50: =UnitEconomics!D9 -> 0.43184641 | D50: =UnitEconomics!E9 -> 0.30667046
A51: Power-price gap vs Ethiopia-linked benchmark | B51: =UnitEconomics!C10 -> 45.99 | C51: =UnitEconomics!D10 -> 25.55 | D51: =UnitEconomics!E10 -> 0
A52: as % of all-in cost | B52: =UnitEconomics!C11 -> 0.18813423 | C52: =UnitEconomics!D11 -> 0.096775494 | D52: =UnitEconomics!E11 -> 0
A54: 8. Reference campus (44 MW, Base case) | B54: Value
A55: NPV ($m) | B55: =UnitEconomics!C36 -> -15.837293
A56: IRR | B56: =UnitEconomics!C37 -> 0.091361627
A57: Break-even fee ($/kW-month) | B57: =UnitEconomics!C42 -> 156.01889
A58: Stabilised EBITDA yield on build cost | B58: =UnitEconomics!C44 -> 0.11625
A60: 9. What it would take (Base supply, Targeted hub, 2030) | B60: Value
A61: Five-lever package (firm MW) | B61: =Levers!C10 -> 805.4
A62: Gap to minimum reserve margin (MW) | B62: =Levers!C13 -> 584.26645
A63: Gap to target reserve margin (MW) | B63: =Levers!C14 -> 753.74527
A64: Coverage of the target-margin gap (x) | B64: =Levers!C16 -> 1.0685308
A65: Indicative package cost ($m/yr) | B65: =Levers!G10 -> 287.13044
A66: Reserve margin in 2030 after the package | B66: =Levers!C17 -> 0.16523929
A67: Share of package supplied by data centres themselves | B67: =Levers!C18 -> 0.1929476
A68: Hub's share of the target-margin gap | B68: =Levers!C19 -> 0.20617045

Sheet Inputs
A1: Inputs and assumptions
A2: Blue = hard-coded input. Yellow fill = key lever. Tag: [S] sourced (see Sources sheet) / [A] analyst assumption. Scenario-invariant inputs are entered once in the Base column.
A4: ID | B4: Parameter | C4: Unit | D4: Stress | E4: Base | F4: Favourable | G4: Tag | H4: Source / rationale
A5: A. Grid baseline (June 2026) | D5: Stress | E5: Base | F5: Favourable
A6: peak0 | B6: Peak demand, June 2026 | C6: MW | D6: =E6 -> 2514 | E6: 2514 | F6: =E6 -> 2514 | G6: [S] | H6: S2: Kenya Power peak demand 2,514 MW in June 2026 (2,549 MW in July 2026).
A7: rm0 | B7: Reserve margin applied to the June 2026 peak | C7: % | D7: -0.015 | E7: 0.0334 | F7: 0.2073 | G7: [S] | H7: S3: -1.5% over the 12 months to Jun 2026 (Stress). S2: 3.34% in Jun 2026 (Base). S2: 20.73% in Jan 2026 - Favourable assumes January-level availability is restored and sustained. IEA comfortable range 20-35% (S1).
A8: growth | B8: Peak-demand growth per year (excluding the hub programme) | C8: %/yr | D8: 0.08 | E8: 0.065 | F8: 0.05 | G8: [S/A] | H8: S2: official projection c.5%/yr (Favourable). Observed: 6.4% FY24-FY25 and 8.5% FY25-Jun 2026 (S2 data) -> Base 6.5%, Stress 8%.
A9: B. Firm, evening-capable supply additions (MW) | D9: Stress | E9: Base | F9: Favourable
A10: eth_mw | B10: Ethiopia import uplift (200 -> 400 MW) | C10: MW | D10: 100 | E10: 200 | F10: 200 | G10: [S/A] | H10: S2: Ethiopia imports of 200 MW 'expected to double'; S19: PPA allows up to 400 MW. Stress assumes only half the uplift is delivered.
A11: eth_yr | B11: Ethiopia uplift: first year counted in annual peak | C11: year | D11: 2028 | E11: 2027 | F11: 2027 | G11: [A] | H11: S2 says 'from December' without a year; Base assumes Dec 2026 so 2027 is the first full peak year (conflict C3).
A12: olk1_mw | B12: Olkaria I rehabilitation (45 -> 61 MW) | C12: MW | D12: =E12 -> 16 | E12: 16 | F12: =E12 -> 16 | G12: [S] | H12: S13: +16 MW, late 2026.
A13: olk1_yr | B13: Olkaria I: first year counted | C13: year | D13: 2028 | E13: 2027 | F13: 2027 | G13: [A] | H13: S13 says late 2026 -> first full peak year 2027.
A14: bess_mw | B14: Battery storage (KenGen BESS), evening-firm MW | C14: MW | D14: =E14 -> 100 | E14: 100 | F14: =E14 -> 100 | G14: [S] | H14: S13: 100 MW battery system planned for 2027; counted at full rating for a 4-hour evening peak.
A15: bess_yr | B15: BESS: first year counted | C15: year | D15: 2028 | E15: 2027 | F15: 2027 | G15: [S/A] | H15: S13: 2027. Stress delays one year.
A16: bess2_mw | B16: Additional storage procured through auctions | C16: MW | D16: 0 | E16: 0 | F16: 100 | G16: [A] | H16: S14: BESS to be competitively sourced inside the auction framework. Only the Favourable case assumes an extra 100 MW.
A17: bess2_yr | B17: Additional storage: first year counted | C17: year | D17: =E17 -> 2029 | E17: 2029 | F17: =E17 -> 2029 | G17: [A] | H17: Earliest realistic COD given S14 timelines (auction -> PPA -> financial close -> COD).
A18: olk7_mw | B18: Olkaria VII geothermal | C18: MW | D18: =E18 -> 80.3 | E18: 80.3 | F18: =E18 -> 80.3 | G18: [S] | H18: S13: 80.3 MW under development; commissioning date not stated.
A19: olk7_yr | B19: Olkaria VII: first year counted | C19: year | D19: 2030 | E19: 2029 | F19: 2028 | G19: [A] | H19: S13 gives no date. Base assumes 2029.
A20: solar_mw | B20: Seven Forks solar | C20: MW | D20: =E20 -> 42.5 | E20: 42.5 | F20: =E20 -> 42.5 | G20: [S] | H20: S13: 42.5 MW solar.
A21: solar_firm | B21: Seven Forks: share counted at the evening peak | C21: % | D21: =E21 -> 0 | E21: 0 | F21: =E21 -> 0 | G21: [A] | H21: S2: solar output falls away as the 6-10pm peak arrives, so solar adds nothing to the evening reserve margin.
A22: solar_yr | B22: Seven Forks: first year counted | C22: year | D22: =E22 -> 2028 | E22: 2028 | F22: =E22 -> 2028 | G22: [A] | H22: Date not stated in S13; irrelevant while the evening contribution is 0%.
A23: auction_mw | B23: New auction-procured firm capacity, per year from the first COD year | C23: MW/yr | D23: 0 | E23: 150 | F23: 300 | G23: [A] | H23: S14: auctions operational within 12 months; financial close 9-12 months after PPA; COD 24-30 months after financial close -> first COD c.2030. Volume is an assumption: Stress none, Base 150 MW/yr, Favourable 300 MW/yr.
A24: auction_yr | B24: First COD year of auction-procured capacity | C24: year | D24: =E24 -> 2030 | E24: 2030 | F24: =E24 -> 2030 | G24: [S/A] | H24: Derived from the S14 timeline.
A25: C. Data-centre demand (hub cases) | D25: Status quo | E25: Targeted hub | F25: Ambitious hub
A26: africa2030 | B26: Africa data-centre capacity in 2030 (midpoint of 1.5-2.2 GW) | C26: MW | D26: =E26 -> 1850 | E26: 1850 | F26: =E26 -> 1850 | G26: [S] | H26: S12: McKinsey range 1.5-2.2 GW by 2030; midpoint used.
A27: share | B27: Kenya share of Africa data-centre capacity in 2030 | C27: % | D27: 0.04 | E27: 0.12 | F27: 0.2 | G27: [S/A] | H27: Status quo = Kenya's current share (c.20 MW of >500 MW, S9/S11 = 4%). Targeted = announced pipeline delivered (c.220 MW, S9). Ambitious = 20%, comparable to a clear No.2 hub.
A28: it2026 | B28: Kenya data-centre IT capacity, 2026 | C28: MW | D28: =E28 -> 45 | E28: 45 | F28: =E28 -> 45 | G28: [S] | H28: S9: almost 20 MW existing plus almost 25 MW expected by end-2025.
A29: pue | B29: Power usage effectiveness (PUE) | C29: x | D29: =E29 -> 1.4 | E29: 1.4 | F29: =E29 -> 1.4 | G29: [A] | H29: Typical 1.3-1.5 for a temperate-altitude site such as Nairobi; grid MW = IT MW x PUE.
A30: util | B30: Average IT utilisation (flat load at the evening peak) | C30: % | D30: =E30 -> 0.75 | E30: 0.75 | F30: =E30 -> 0.75 | G30: [A] | H30: Contracted-and-drawing share of installed IT capacity at maturity; data-centre load is near-flat so peak = average.
A31: D. Economics | D31: Stress | E31: Base | F31: Favourable
A32: fee | B32: Colocation infrastructure fee (ex-power) | C32: $/kW-month | D32: 110 | E32: 150 | F32: 200 | G32: [A] | H32: No public Kenyan price (paywalled in S9). Range spans typical wholesale-to-retail colocation. Replace with operator quotes before relying on it.
A33: capex | B33: Data-centre build cost | C33: $m per IT MW | D33: 11.3 | E33: 8 | F33: 7 | G33: [S] | H33: S21: JLL global average $11.3m/MW (Stress); emerging markets below $8m/MW (Base).
A34: campus_mw | B34: Average campus size | C34: MW IT | D34: =E34 -> 35 | E34: 35 | F34: =E34 -> 35 | G34: [A] | H34: Nxtra Tatu City is 44 MW (S10); smaller colocation sites pull the average down.
A35: jobs | B35: Operational jobs per campus | C35: jobs | D35: 100 | E35: 150 | F35: 200 | G35: [S] | H35: S22: roughly 100-200 jobs at a typical treated US county; colocation is 'modest'.
A36: tariff | B36: All-in grid tariff to a large data-centre customer | C36: $/kWh | D36: 0.11 | E36: 0.09 | F36: 0.065 | G36: [S/A] | H36: S18: KSh 7.99/kWh (2020); S16: April 2026 pass-throughs add c.KSh 4.7/kWh; S15: wholesale c.$0.07. At c.KSh 129/$ (S15 implied) the range is $0.065-0.11 (conflict C5).
A37: eth_price | B37: Benchmark: Ethiopia-to-Kenya wholesale price | C37: $/kWh | D37: =E37 -> 0.065 | E37: 0.065 | F37: =E37 -> 0.065 | G37: [S] | H37: S19: 6.5 US cents/kWh PPA price.
A38: lcos | B38: Cost of shifting energy through a 4-hour battery (global benchmark) | C38: $/MWh | D38: =E38 -> 78 | E38: 78 | F38: =E38 -> 78 | G38: [S] | H38: S23: BNEF 2025 four-hour battery LCOE.
A39: em_prem | B39: Emerging-market premium on storage cost | C39: x | D39: =E39 -> 1.5 | E39: 1.5 | F39: =E39 -> 1.5 | G39: [A] | H39: Financing, import and logistics premium over the global benchmark.
A40: hours | B40: Evening peak hours to cover | C40: hours/day | D40: =E40 -> 4 | E40: 4 | F40: =E40 -> 4 | G40: [S] | H40: S2: evening peak c.6pm-10pm.
A41: rte | B41: Battery round-trip efficiency | C41: % | D41: =E41 -> 0.85 | E41: 0.85 | F41: =E41 -> 0.85 | G41: [A] | H41: Typical lithium-ion utility-scale range 80-90%.
A42: charge_price | B42: Energy price paid to recharge the battery | C42: $/MWh | D42: =E42 -> 70 | E42: 70 | F42: =E42 -> 70 | G42: [S] | H42: S15: wholesale c.$0.07/kWh.
A43: min_rm | B43: Minimum reserve margin before connecting new hub load | C43: % | D43: =E43 -> 0.1 | E43: 0.1 | F43: =E43 -> 0.1 | G43: [A] | H43: Gate threshold. Below the IEA 20-35% comfortable range (S1) but well above the 3.3% of Jun 2026.
A44: target_rm | B44: Target reserve margin to restore | C44: % | D44: =E44 -> 0.15 | E44: 0.15 | F44: =E44 -> 0.15 | G44: [A] | H44: Planning target; sensitivity on the Matrix sheet.
A45: E. Reference campus (Nxtra-scale, 44 MW in two phases)
A46: mw1 | B46: Phase 1 IT capacity | C46: MW | D46: =E46 -> 22 | E46: 22 | F46: =E46 -> 22 | G46: [S] | H46: S10: two phases of 22 MW.
A47: mw2 | B47: Phase 2 IT capacity | C47: MW | D47: =E47 -> 22 | E47: 22 | F47: =E47 -> 22 | G47: [S] | H47: S10.
A48: ph2_off | B48: Phase 2 starts this many years after phase 1 | C48: years | D48: =E48 -> 2 | E48: 2 | F48: =E48 -> 2 | G48: [A] | H48: Typical lag between phases.
A49: wacc | B49: Discount rate (USD, pre-tax, unlevered) | C49: % | D49: =E49 -> 0.1 | E49: 0.1 | F49: =E49 -> 0.1 | G49: [A] | H49: Hurdle for emerging-market digital infrastructure with some DFI participation. Sensitivity on UnitEconomics.
A50: opex_pct | B50: Variable opex (staff, maintenance, insurance, connectivity) | C50: % of revenue | D50: =E50 -> 0.2 | E50: 0.2 | F50: =E50 -> 0.2 | G50: [A] | H50: Analyst assumption.
A51: fixed_opex | B51: Fixed opex | C51: $m per installed MW per year | D51: =E51 -> 0.15 | E51: 0.15 | F51: =E51 -> 0.15 | G51: [A] | H51: Analyst assumption.
A52: maint | B52: Maintenance capex | C52: % of cumulative growth capex per year | D52: =E52 -> 0.015 | E52: 0.015 | F52: =E52 -> 0.015 | G52: [A] | H52: Analyst assumption.
A53: tv_mult | B53: Terminal value at end of horizon | C53: x EBITDA | D53: =E53 -> 7 | E53: 7 | F53: =E53 -> 7 | G53: [A] | H53: Conservative versus 15-20 year asset life; set to 0 to see the no-terminal-value case.
A54: start_year | B54: Campus phase 1 first operating year | C54: year | D54: =E54 -> 2027 | E54: 2027 | F54: =E54 -> 2027 | G54: [S] | H54: S10: ready for service Q1 2027.
A55: F. 'What it would take' package (Base supply, Targeted hub)
A56: lv_storage | B56: Utility-scale 4-hour storage procured through auctions | C56: MW | D56: =E56 -> 250 | E56: 250 | F56: =E56 -> 250 | G56: [A] | H56: S14: BESS to be competitively sourced; S13: first 100 MW due 2027. Size is an assumption.
A57: lv_import | B57: Second Ethiopia import tranche (beyond the 400 MW PPA cap) | C57: MW | D57: =E57 -> 150 | E57: 150 | F57: =E57 -> 150 | G57: [A] | H57: S2: Ethiopia has large hydro surplus; S19: current PPA caps at 400 MW. Size is an assumption.
A58: lv_geo | B58: Accelerated geothermal (Olkaria VII pull-forward + mobile wellhead units) | C58: MW | D58: =E58 -> 100 | E58: 100 | F58: =E58 -> 100 | G58: [A] | H58: S13: wellhead units 'by 2027' (MW not stated); Olkaria VII 80.3 MW. Size is an assumption.
A59: lv_auction | B59: Auction tranche pulled forward one year | C59: MW | D59: =E59 -> 150 | E59: 150 | F59: =E59 -> 150 | G59: [A] | H59: S14: first COD c.2030 on the stated timeline; pull-forward needs procurement and financial-close discipline.
A60: lf_import | B60: Load factor of imported power | C60: % | D60: =E60 -> 0.85 | E60: 0.85 | F60: =E60 -> 0.85 | G60: [A] | H60: Analyst assumption for indicative energy cost.
A61: lf_geo | B61: Load factor of geothermal / new firm generation | C61: % | D61: =E61 -> 0.9 | E61: 0.9 | F61: =E61 -> 0.9 | G61: [A] | H61: Geothermal runs near-baseload; analyst assumption.

Sheet Grid
A1: Grid headroom, 2026-2032: firm evening-capable supply versus peak demand (before any hub load)
A2: Each block is one supply scenario. Negative reserve margin = unserved peak (rationing) unless emergency capacity is bought; it measures the size of the response needed.
A4: Stress supply case | B4: Unit | C4: 2026 | D4: 2027 | E4: 2028 | F4: 2029 | G4: 2030 | H4: 2031 | I4: 2032
A5: Peak demand | B5: MW | C5: =Inputs!$D$6 -> 2514 | D5: =C5*(1+Inputs!$D$8) -> 2715.12 | E5: =D5*(1+Inputs!$D$8) -> 2932.3296 | F5: =E5*(1+Inputs!$D$8) -> 3166.916 | G5: =F5*(1+Inputs!$D$8) -> 3420.2692 | H5: =G5*(1+Inputs!$D$8) -> 3693.8908 | I5: =H5*(1+Inputs!$D$8) -> 3989.402
A6: Baseline firm available capacity (Jun 2026, incl. imports) | B6: MW | C6: =Inputs!$D$6*(1+Inputs!$D$7) -> 2476.29 | D6: =Inputs!$D$6*(1+Inputs!$D$7) -> 2476.29 | E6: =Inputs!$D$6*(1+Inputs!$D$7) -> 2476.29 | F6: =Inputs!$D$6*(1+Inputs!$D$7) -> 2476.29 | G6: =Inputs!$D$6*(1+Inputs!$D$7) -> 2476.29 | H6: =Inputs!$D$6*(1+Inputs!$D$7) -> 2476.29 | I6: =Inputs!$D$6*(1+Inputs!$D$7) -> 2476.29
A7: + Ethiopia import uplift | B7: MW | C7: =IF(C$4>=Inputs!$D$11,Inputs!$D$10,0) -> 0 | D7: =IF(D$4>=Inputs!$D$11,Inputs!$D$10,0) -> 0 | E7: =IF(E$4>=Inputs!$D$11,Inputs!$D$10,0) -> 100 | F7: =IF(F$4>=Inputs!$D$11,Inputs!$D$10,0) -> 100 | G7: =IF(G$4>=Inputs!$D$11,Inputs!$D$10,0) -> 100 | H7: =IF(H$4>=Inputs!$D$11,Inputs!$D$10,0) -> 100 | I7: =IF(I$4>=Inputs!$D$11,Inputs!$D$10,0) -> 100
A8: + Olkaria I rehabilitation | B8: MW | C8: =IF(C$4>=Inputs!$D$13,Inputs!$D$12,0) -> 0 | D8: =IF(D$4>=Inputs!$D$13,Inputs!$D$12,0) -> 0 | E8: =IF(E$4>=Inputs!$D$13,Inputs!$D$12,0) -> 16 | F8: =IF(F$4>=Inputs!$D$13,Inputs!$D$12,0) -> 16 | G8: =IF(G$4>=Inputs!$D$13,Inputs!$D$12,0) -> 16 | H8: =IF(H$4>=Inputs!$D$13,Inputs!$D$12,0) -> 16 | I8: =IF(I$4>=Inputs!$D$13,Inputs!$D$12,0) -> 16
A9: + Battery storage (KenGen BESS) | B9: MW | C9: =IF(C$4>=Inputs!$D$15,Inputs!$D$14,0) -> 0 | D9: =IF(D$4>=Inputs!$D$15,Inputs!$D$14,0) -> 0 | E9: =IF(E$4>=Inputs!$D$15,Inputs!$D$14,0) -> 100 | F9: =IF(F$4>=Inputs!$D$15,Inputs!$D$14,0) -> 100 | G9: =IF(G$4>=Inputs!$D$15,Inputs!$D$14,0) -> 100 | H9: =IF(H$4>=Inputs!$D$15,Inputs!$D$14,0) -> 100 | I9: =IF(I$4>=Inputs!$D$15,Inputs!$D$14,0) -> 100
A10: + Additional storage (auctions) | B10: MW | C10: =IF(C$4>=Inputs!$D$17,Inputs!$D$16,0) -> 0 | D10: =IF(D$4>=Inputs!$D$17,Inputs!$D$16,0) -> 0 | E10: =IF(E$4>=Inputs!$D$17,Inputs!$D$16,0) -> 0 | F10: =IF(F$4>=Inputs!$D$17,Inputs!$D$16,0) -> 0 | G10: =IF(G$4>=Inputs!$D$17,Inputs!$D$16,0) -> 0 | H10: =IF(H$4>=Inputs!$D$17,Inputs!$D$16,0) -> 0 | I10: =IF(I$4>=Inputs!$D$17,Inputs!$D$16,0) -> 0
A11: + Olkaria VII geothermal | B11: MW | C11: =IF(C$4>=Inputs!$D$19,Inputs!$D$18,0) -> 0 | D11: =IF(D$4>=Inputs!$D$19,Inputs!$D$18,0) -> 0 | E11: =IF(E$4>=Inputs!$D$19,Inputs!$D$18,0) -> 0 | F11: =IF(F$4>=Inputs!$D$19,Inputs!$D$18,0) -> 0 | G11: =IF(G$4>=Inputs!$D$19,Inputs!$D$18,0) -> 80.3 | H11: =IF(H$4>=Inputs!$D$19,Inputs!$D$18,0) -> 80.3 | I11: =IF(I$4>=Inputs!$D$19,Inputs!$D$18,0) -> 80.3
A12: + Seven Forks solar (evening-firm share only) | B12: MW | C12: =IF(C$4>=Inputs!$D$22,Inputs!$D$20*Inputs!$D$21,0) -> 0 | D12: =IF(D$4>=Inputs!$D$22,Inputs!$D$20*Inputs!$D$21,0) -> 0 | E12: =IF(E$4>=Inputs!$D$22,Inputs!$D$20*Inputs!$D$21,0) -> 0 | F12: =IF(F$4>=Inputs!$D$22,Inputs!$D$20*Inputs!$D$21,0) -> 0 | G12: =IF(G$4>=Inputs!$D$22,Inputs!$D$20*Inputs!$D$21,0) -> 0 | H12: =IF(H$4>=Inputs!$D$22,Inputs!$D$20*Inputs!$D$21,0) -> 0 | I12: =IF(I$4>=Inputs!$D$22,Inputs!$D$20*Inputs!$D$21,0) -> 0
A13: + Auction-procured firm capacity (cumulative) | B13: MW | C13: =Inputs!$D$23*MAX(0,C$4-Inputs!$D$24+1) -> 0 | D13: =Inputs!$D$23*MAX(0,D$4-Inputs!$D$24+1) -> 0 | E13: =Inputs!$D$23*MAX(0,E$4-Inputs!$D$24+1) -> 0 | F13: =Inputs!$D$23*MAX(0,F$4-Inputs!$D$24+1) -> 0 | G13: =Inputs!$D$23*MAX(0,G$4-Inputs!$D$24+1) -> 0 | H13: =Inputs!$D$23*MAX(0,H$4-Inputs!$D$24+1) -> 0 | I13: =Inputs!$D$23*MAX(0,I$4-Inputs!$D$24+1) -> 0
A14: Firm evening-capable capacity | B14: MW | C14: =C6+SUM(C7:C13) -> 2476.29 | D14: =D6+SUM(D7:D13) -> 2476.29 | E14: =E6+SUM(E7:E13) -> 2692.29 | F14: =F6+SUM(F7:F13) -> 2692.29 | G14: =G6+SUM(G7:G13) -> 2772.59 | H14: =H6+SUM(H7:H13) -> 2772.59 | I14: =I6+SUM(I7:I13) -> 2772.59
A15: Reserve margin before hub load | B15: % | C15: =C14/C5-1 -> -0.015 | D15: =D14/D5-1 -> -0.087962963 | E15: =E14/E5-1 -> -0.081859693 | F15: =F14/F5-1 -> -0.14987009 | G15: =G14/G5-1 -> -0.18936499 | H15: =H14/H5-1 -> -0.24941203 | I15: =I14/I5-1 -> -0.30501114
A16: Spare MW (firm capacity minus peak) | B16: MW | C16: =C14-C5 -> -37.71 | D16: =D14-D5 -> -238.83 | E16: =E14-E5 -> -240.0396 | F16: =F14-F5 -> -474.62597 | G16: =G14-G5 -> -647.67925 | H16: =H14-H5 -> -921.30079 | I16: =I14-I5 -> -1216.812
A17: New firm MW needed each year just to hold the margin | B17: MW/yr | D17: =D5-C5 -> 201.12 | E17: =E5-D5 -> 217.2096 | F17: =F5-E5 -> 234.58637 | G17: =G5-F5 -> 253.35328 | H17: =H5-G5 -> 273.62154 | I17: =I5-H5 -> 295.51126
A19: Base supply case | B19: Unit | C19: 2026 | D19: 2027 | E19: 2028 | F19: 2029 | G19: 2030 | H19: 2031 | I19: 2032
A20: Peak demand | B20: MW | C20: =Inputs!$E$6 -> 2514 | D20: =C20*(1+Inputs!$E$8) -> 2677.41 | E20: =D20*(1+Inputs!$E$8) -> 2851.4417 | F20: =E20*(1+Inputs!$E$8) -> 3036.7854 | G20: =F20*(1+Inputs!$E$8) -> 3234.1764 | H20: =G20*(1+Inputs!$E$8) -> 3444.3979 | I20: =H20*(1+Inputs!$E$8) -> 3668.2837
A21: Baseline firm available capacity (Jun 2026, incl. imports) | B21: MW | C21: =Inputs!$E$6*(1+Inputs!$E$7) -> 2597.9676 | D21: =Inputs!$E$6*(1+Inputs!$E$7) -> 2597.9676 | E21: =Inputs!$E$6*(1+Inputs!$E$7) -> 2597.9676 | F21: =Inputs!$E$6*(1+Inputs!$E$7) -> 2597.9676 | G21: =Inputs!$E$6*(1+Inputs!$E$7) -> 2597.9676 | H21: =Inputs!$E$6*(1+Inputs!$E$7) -> 2597.9676 | I21: =Inputs!$E$6*(1+Inputs!$E$7) -> 2597.9676
A22: + Ethiopia import uplift | B22: MW | C22: =IF(C$19>=Inputs!$E$11,Inputs!$E$10,0) -> 0 | D22: =IF(D$19>=Inputs!$E$11,Inputs!$E$10,0) -> 200 | E22: =IF(E$19>=Inputs!$E$11,Inputs!$E$10,0) -> 200 | F22: =IF(F$19>=Inputs!$E$11,Inputs!$E$10,0) -> 200 | G22: =IF(G$19>=Inputs!$E$11,Inputs!$E$10,0) -> 200 | H22: =IF(H$19>=Inputs!$E$11,Inputs!$E$10,0) -> 200 | I22: =IF(I$19>=Inputs!$E$11,Inputs!$E$10,0) -> 200
A23: + Olkaria I rehabilitation | B23: MW | C23: =IF(C$19>=Inputs!$E$13,Inputs!$E$12,0) -> 0 | D23: =IF(D$19>=Inputs!$E$13,Inputs!$E$12,0) -> 16 | E23: =IF(E$19>=Inputs!$E$13,Inputs!$E$12,0) -> 16 | F23: =IF(F$19>=Inputs!$E$13,Inputs!$E$12,0) -> 16 | G23: =IF(G$19>=Inputs!$E$13,Inputs!$E$12,0) -> 16 | H23: =IF(H$19>=Inputs!$E$13,Inputs!$E$12,0) -> 16 | I23: =IF(I$19>=Inputs!$E$13,Inputs!$E$12,0) -> 16
A24: + Battery storage (KenGen BESS) | B24: MW | C24: =IF(C$19>=Inputs!$E$15,Inputs!$E$14,0) -> 0 | D24: =IF(D$19>=Inputs!$E$15,Inputs!$E$14,0) -> 100 | E24: =IF(E$19>=Inputs!$E$15,Inputs!$E$14,0) -> 100 | F24: =IF(F$19>=Inputs!$E$15,Inputs!$E$14,0) -> 100 | G24: =IF(G$19>=Inputs!$E$15,Inputs!$E$14,0) -> 100 | H24: =IF(H$19>=Inputs!$E$15,Inputs!$E$14,0) -> 100 | I24: =IF(I$19>=Inputs!$E$15,Inputs!$E$14,0) -> 100
A25: + Additional storage (auctions) | B25: MW | C25: =IF(C$19>=Inputs!$E$17,Inputs!$E$16,0) -> 0 | D25: =IF(D$19>=Inputs!$E$17,Inputs!$E$16,0) -> 0 | E25: =IF(E$19>=Inputs!$E$17,Inputs!$E$16,0) -> 0 | F25: =IF(F$19>=Inputs!$E$17,Inputs!$E$16,0) -> 0 | G25: =IF(G$19>=Inputs!$E$17,Inputs!$E$16,0) -> 0 | H25: =IF(H$19>=Inputs!$E$17,Inputs!$E$16,0) -> 0 | I25: =IF(I$19>=Inputs!$E$17,Inputs!$E$16,0) -> 0
A26: + Olkaria VII geothermal | B26: MW | C26: =IF(C$19>=Inputs!$E$19,Inputs!$E$18,0) -> 0 | D26: =IF(D$19>=Inputs!$E$19,Inputs!$E$18,0) -> 0 | E26: =IF(E$19>=Inputs!$E$19,Inputs!$E$18,0) -> 0 | F26: =IF(F$19>=Inputs!$E$19,Inputs!$E$18,0) -> 80.3 | G26: =IF(G$19>=Inputs!$E$19,Inputs!$E$18,0) -> 80.3 | H26: =IF(H$19>=Inputs!$E$19,Inputs!$E$18,0) -> 80.3 | I26: =IF(I$19>=Inputs!$E$19,Inputs!$E$18,0) -> 80.3
A27: + Seven Forks solar (evening-firm share only) | B27: MW | C27: =IF(C$19>=Inputs!$E$22,Inputs!$E$20*Inputs!$E$21,0) -> 0 | D27: =IF(D$19>=Inputs!$E$22,Inputs!$E$20*Inputs!$E$21,0) -> 0 | E27: =IF(E$19>=Inputs!$E$22,Inputs!$E$20*Inputs!$E$21,0) -> 0 | F27: =IF(F$19>=Inputs!$E$22,Inputs!$E$20*Inputs!$E$21,0) -> 0 | G27: =IF(G$19>=Inputs!$E$22,Inputs!$E$20*Inputs!$E$21,0) -> 0 | H27: =IF(H$19>=Inputs!$E$22,Inputs!$E$20*Inputs!$E$21,0) -> 0 | I27: =IF(I$19>=Inputs!$E$22,Inputs!$E$20*Inputs!$E$21,0) -> 0
A28: + Auction-procured firm capacity (cumulative) | B28: MW | C28: =Inputs!$E$23*MAX(0,C$19-Inputs!$E$24+1) -> 0 | D28: =Inputs!$E$23*MAX(0,D$19-Inputs!$E$24+1) -> 0 | E28: =Inputs!$E$23*MAX(0,E$19-Inputs!$E$24+1) -> 0 | F28: =Inputs!$E$23*MAX(0,F$19-Inputs!$E$24+1) -> 0 | G28: =Inputs!$E$23*MAX(0,G$19-Inputs!$E$24+1) -> 150 | H28: =Inputs!$E$23*MAX(0,H$19-Inputs!$E$24+1) -> 300 | I28: =Inputs!$E$23*MAX(0,I$19-Inputs!$E$24+1) -> 450
A29: Firm evening-capable capacity | B29: MW | C29: =C21+SUM(C22:C28) -> 2597.9676 | D29: =D21+SUM(D22:D28) -> 2913.9676 | E29: =E21+SUM(E22:E28) -> 2913.9676 | F29: =F21+SUM(F22:F28) -> 2994.2676 | G29: =G21+SUM(G22:G28) -> 3144.2676 | H29: =H21+SUM(H22:H28) -> 3294.2676 | I29: =I21+SUM(I22:I28) -> 3444.2676
A30: Reserve margin before hub load | B30: % | C30: =C29/C20-1 -> 0.0334 | D30: =D29/D20-1 -> 0.088353147 | E30: =E29/E20-1 -> 0.021927838 | F30: =F29/F20-1 -> -0.01400091 | G30: =G29/G20-1 -> -0.027799598 | H30: =H29/H20-1 -> -0.043586797 | I30: =I29/I20-1 -> -0.061068377
A31: Spare MW (firm capacity minus peak) | B31: MW | C31: =C29-C20 -> 83.9676 | D31: =D29-D20 -> 236.5576 | E31: =E29-E20 -> 62.52595 | F31: =F29-F20 -> -42.517757 | G31: =G29-G20 -> -89.908805 | H31: =H29-H20 -> -150.13027 | I31: =I29-I20 -> -224.01613
A32: New firm MW needed each year just to hold the margin | B32: MW/yr | D32: =D20-C20 -> 163.41 | E32: =E20-D20 -> 174.03165 | F32: =F20-E20 -> 185.34371 | G32: =G20-F20 -> 197.39105 | H32: =H20-G20 -> 210.22147 | I32: =I20-H20 -> 223.88586
A34: Favourable supply case | B34: Unit | C34: 2026 | D34: 2027 | E34: 2028 | F34: 2029 | G34: 2030 | H34: 2031 | I34: 2032
A35: Peak demand | B35: MW | C35: =Inputs!$F$6 -> 2514 | D35: =C35*(1+Inputs!$F$8) -> 2639.7 | E35: =D35*(1+Inputs!$F$8) -> 2771.685 | F35: =E35*(1+Inputs!$F$8) -> 2910.2692 | G35: =F35*(1+Inputs!$F$8) -> 3055.7827 | H35: =G35*(1+Inputs!$F$8) -> 3208.5718 | I35: =H35*(1+Inputs!$F$8) -> 3369.0004
A36: Baseline firm available capacity (Jun 2026, incl. imports) | B36: MW | C36: =Inputs!$F$6*(1+Inputs!$F$7) -> 3035.1522 | D36: =Inputs!$F$6*(1+Inputs!$F$7) -> 3035.1522 | E36: =Inputs!$F$6*(1+Inputs!$F$7) -> 3035.1522 | F36: =Inputs!$F$6*(1+Inputs!$F$7) -> 3035.1522 | G36: =Inputs!$F$6*(1+Inputs!$F$7) -> 3035.1522 | H36: =Inputs!$F$6*(1+Inputs!$F$7) -> 3035.1522 | I36: =Inputs!$F$6*(1+Inputs!$F$7) -> 3035.1522
A37: + Ethiopia import uplift | B37: MW | C37: =IF(C$34>=Inputs!$F$11,Inputs!$F$10,0) -> 0 | D37: =IF(D$34>=Inputs!$F$11,Inputs!$F$10,0) -> 200 | E37: =IF(E$34>=Inputs!$F$11,Inputs!$F$10,0) -> 200 | F37: =IF(F$34>=Inputs!$F$11,Inputs!$F$10,0) -> 200 | G37: =IF(G$34>=Inputs!$F$11,Inputs!$F$10,0) -> 200 | H37: =IF(H$34>=Inputs!$F$11,Inputs!$F$10,0) -> 200 | I37: =IF(I$34>=Inputs!$F$11,Inputs!$F$10,0) -> 200
A38: + Olkaria I rehabilitation | B38: MW | C38: =IF(C$34>=Inputs!$F$13,Inputs!$F$12,0) -> 0 | D38: =IF(D$34>=Inputs!$F$13,Inputs!$F$12,0) -> 16 | E38: =IF(E$34>=Inputs!$F$13,Inputs!$F$12,0) -> 16 | F38: =IF(F$34>=Inputs!$F$13,Inputs!$F$12,0) -> 16 | G38: =IF(G$34>=Inputs!$F$13,Inputs!$F$12,0) -> 16 | H38: =IF(H$34>=Inputs!$F$13,Inputs!$F$12,0) -> 16 | I38: =IF(I$34>=Inputs!$F$13,Inputs!$F$12,0) -> 16
A39: + Battery storage (KenGen BESS) | B39: MW | C39: =IF(C$34>=Inputs!$F$15,Inputs!$F$14,0) -> 0 | D39: =IF(D$34>=Inputs!$F$15,Inputs!$F$14,0) -> 100 | E39: =IF(E$34>=Inputs!$F$15,Inputs!$F$14,0) -> 100 | F39: =IF(F$34>=Inputs!$F$15,Inputs!$F$14,0) -> 100 | G39: =IF(G$34>=Inputs!$F$15,Inputs!$F$14,0) -> 100 | H39: =IF(H$34>=Inputs!$F$15,Inputs!$F$14,0) -> 100 | I39: =IF(I$34>=Inputs!$F$15,Inputs!$F$14,0) -> 100
A40: + Additional storage (auctions) | B40: MW | C40: =IF(C$34>=Inputs!$F$17,Inputs!$F$16,0) -> 0 | D40: =IF(D$34>=Inputs!$F$17,Inputs!$F$16,0) -> 0 | E40: =IF(E$34>=Inputs!$F$17,Inputs!$F$16,0) -> 0 | F40: =IF(F$34>=Inputs!$F$17,Inputs!$F$16,0) -> 100 | G40: =IF(G$34>=Inputs!$F$17,Inputs!$F$16,0) -> 100 | H40: =IF(H$34>=Inputs!$F$17,Inputs!$F$16,0) -> 100 | I40: =IF(I$34>=Inputs!$F$17,Inputs!$F$16,0) -> 100
A41: + Olkaria VII geothermal | B41: MW | C41: =IF(C$34>=Inputs!$F$19,Inputs!$F$18,0) -> 0 | D41: =IF(D$34>=Inputs!$F$19,Inputs!$F$18,0) -> 0 | E41: =IF(E$34>=Inputs!$F$19,Inputs!$F$18,0) -> 80.3 | F41: =IF(F$34>=Inputs!$F$19,Inputs!$F$18,0) -> 80.3 | G41: =IF(G$34>=Inputs!$F$19,Inputs!$F$18,0) -> 80.3 | H41: =IF(H$34>=Inputs!$F$19,Inputs!$F$18,0) -> 80.3 | I41: =IF(I$34>=Inputs!$F$19,Inputs!$F$18,0) -> 80.3
A42: + Seven Forks solar (evening-firm share only) | B42: MW | C42: =IF(C$34>=Inputs!$F$22,Inputs!$F$20*Inputs!$F$21,0) -> 0 | D42: =IF(D$34>=Inputs!$F$22,Inputs!$F$20*Inputs!$F$21,0) -> 0 | E42: =IF(E$34>=Inputs!$F$22,Inputs!$F$20*Inputs!$F$21,0) -> 0 | F42: =IF(F$34>=Inputs!$F$22,Inputs!$F$20*Inputs!$F$21,0) -> 0 | G42: =IF(G$34>=Inputs!$F$22,Inputs!$F$20*Inputs!$F$21,0) -> 0 | H42: =IF(H$34>=Inputs!$F$22,Inputs!$F$20*Inputs!$F$21,0) -> 0 | I42: =IF(I$34>=Inputs!$F$22,Inputs!$F$20*Inputs!$F$21,0) -> 0
A43: + Auction-procured firm capacity (cumulative) | B43: MW | C43: =Inputs!$F$23*MAX(0,C$34-Inputs!$F$24+1) -> 0 | D43: =Inputs!$F$23*MAX(0,D$34-Inputs!$F$24+1) -> 0 | E43: =Inputs!$F$23*MAX(0,E$34-Inputs!$F$24+1) -> 0 | F43: =Inputs!$F$23*MAX(0,F$34-Inputs!$F$24+1) -> 0 | G43: =Inputs!$F$23*MAX(0,G$34-Inputs!$F$24+1) -> 300 | H43: =Inputs!$F$23*MAX(0,H$34-Inputs!$F$24+1) -> 600 | I43: =Inputs!$F$23*MAX(0,I$34-Inputs!$F$24+1) -> 900
A44: Firm evening-capable capacity | B44: MW | C44: =C36+SUM(C37:C43) -> 3035.1522 | D44: =D36+SUM(D37:D43) -> 3351.1522 | E44: =E36+SUM(E37:E43) -> 3431.4522 | F44: =F36+SUM(F37:F43) -> 3531.4522 | G44: =G36+SUM(G37:G43) -> 3831.4522 | H44: =H36+SUM(H37:H43) -> 4131.4522 | I44: =I36+SUM(I37:I43) -> 4431.4522
A45: Reserve margin before hub load | B45: % | C45: =C44/C35-1 -> 0.2073 | D45: =D44/D35-1 -> 0.2695201 | E45: =E44/E35-1 -> 0.23803831 | F45: =F44/F35-1 -> 0.21344518 | G45: =G44/G35-1 -> 0.2538366 | H45: =H44/H35-1 -> 0.28762964 | I45: =I44/I35-1 -> 0.31536112
A46: Spare MW (firm capacity minus peak) | B46: MW | C46: =C44-C35 -> 521.1522 | D46: =D44-D35 -> 711.4522 | E46: =E44-E35 -> 659.7672 | F46: =F44-F35 -> 621.18295 | G46: =G44-G35 -> 775.66949 | H46: =H44-H35 -> 922.88035 | I46: =I44-I35 -> 1062.4518
A47: New firm MW needed each year just to hold the margin | B47: MW/yr | D47: =D35-C35 -> 125.7 | E47: =E35-D35 -> 131.985 | F47: =F35-E35 -> 138.58425 | G47: =G35-F35 -> 145.51346 | H47: =H35-G35 -> 152.78914 | I47: =I35-H35 -> 160.42859

Sheet Hub
A1: Data-centre demand and the size of the prize, 2026-2032
A2: Kenya IT capacity moves linearly from 2026 to the 2030 target (share of Africa capacity) and keeps that pace afterwards. Grid load counts only capacity above the Status quo case, because Status quo growth is already inside the peak-demand growth rate.
A4: Status quo | B4: Unit | C4: 2026 | D4: 2027 | E4: 2028 | F4: 2029 | G4: 2030 | H4: 2031 | I4: 2032
A5: Kenya data-centre IT capacity | B5: MW IT | C5: =Inputs!$D$28+(Inputs!$D$27*Inputs!$D$26-Inputs!$D$28)*(C$4-2026)/4 -> 45 | D5: =Inputs!$D$28+(Inputs!$D$27*Inputs!$D$26-Inputs!$D$28)*(D$4-2026)/4 -> 52.25 | E5: =Inputs!$D$28+(Inputs!$D$27*Inputs!$D$26-Inputs!$D$28)*(E$4-2026)/4 -> 59.5 | F5: =Inputs!$D$28+(Inputs!$D$27*Inputs!$D$26-Inputs!$D$28)*(F$4-2026)/4 -> 66.75 | G5: =Inputs!$D$28+(Inputs!$D$27*Inputs!$D$26-Inputs!$D$28)*(G$4-2026)/4 -> 74 | H5: =Inputs!$D$28+(Inputs!$D$27*Inputs!$D$26-Inputs!$D$28)*(H$4-2026)/4 -> 81.25 | I5: =Inputs!$D$28+(Inputs!$D$27*Inputs!$D$26-Inputs!$D$28)*(I$4-2026)/4 -> 88.5
A6: IT capacity above Status quo | B6: MW IT | C6: =MAX(0,C5-C5) -> 0 | D6: =MAX(0,D5-D5) -> 0 | E6: =MAX(0,E5-E5) -> 0 | F6: =MAX(0,F5-F5) -> 0 | G6: =MAX(0,G5-G5) -> 0 | H6: =MAX(0,H5-H5) -> 0 | I6: =MAX(0,I5-I5) -> 0
A7: Hub load on the grid at the evening peak | B7: MW | C7: =C6*Inputs!$D$29*Inputs!$D$30 -> 0 | D7: =D6*Inputs!$D$29*Inputs!$D$30 -> 0 | E7: =E6*Inputs!$D$29*Inputs!$D$30 -> 0 | F7: =F6*Inputs!$D$29*Inputs!$D$30 -> 0 | G7: =G6*Inputs!$D$29*Inputs!$D$30 -> 0 | H7: =H6*Inputs!$D$29*Inputs!$D$30 -> 0 | I7: =I6*Inputs!$D$29*Inputs!$D$30 -> 0
A8: Infrastructure-fee revenue pool (Base fee) | B8: $m/yr | C8: =C5*Inputs!$E$30*Inputs!$E$32*12/1000 -> 60.75 | D8: =D5*Inputs!$E$30*Inputs!$E$32*12/1000 -> 70.5375 | E8: =E5*Inputs!$E$30*Inputs!$E$32*12/1000 -> 80.325 | F8: =F5*Inputs!$E$30*Inputs!$E$32*12/1000 -> 90.1125 | G8: =G5*Inputs!$E$30*Inputs!$E$32*12/1000 -> 99.9 | H8: =H5*Inputs!$E$30*Inputs!$E$32*12/1000 -> 109.6875 | I8: =I5*Inputs!$E$30*Inputs!$E$32*12/1000 -> 119.475
A9: Cumulative build investment since 2026 (Base cost) | B9: $m | C9: =(C5-Inputs!$E$28)*Inputs!$E$33 -> 0 | D9: =(D5-Inputs!$E$28)*Inputs!$E$33 -> 58 | E9: =(E5-Inputs!$E$28)*Inputs!$E$33 -> 116 | F9: =(F5-Inputs!$E$28)*Inputs!$E$33 -> 174 | G9: =(G5-Inputs!$E$28)*Inputs!$E$33 -> 232 | H9: =(H5-Inputs!$E$28)*Inputs!$E$33 -> 290 | I9: =(I5-Inputs!$E$28)*Inputs!$E$33 -> 348
A11: Targeted hub | B11: Unit | C11: 2026 | D11: 2027 | E11: 2028 | F11: 2029 | G11: 2030 | H11: 2031 | I11: 2032
A12: Kenya data-centre IT capacity | B12: MW IT | C12: =Inputs!$E$28+(Inputs!$E$27*Inputs!$E$26-Inputs!$E$28)*(C$11-2026)/4 -> 45 | D12: =Inputs!$E$28+(Inputs!$E$27*Inputs!$E$26-Inputs!$E$28)*(D$11-2026)/4 -> 89.25 | E12: =Inputs!$E$28+(Inputs!$E$27*Inputs!$E$26-Inputs!$E$28)*(E$11-2026)/4 -> 133.5 | F12: =Inputs!$E$28+(Inputs!$E$27*Inputs!$E$26-Inputs!$E$28)*(F$11-2026)/4 -> 177.75 | G12: =Inputs!$E$28+(Inputs!$E$27*Inputs!$E$26-Inputs!$E$28)*(G$11-2026)/4 -> 222 | H12: =Inputs!$E$28+(Inputs!$E$27*Inputs!$E$26-Inputs!$E$28)*(H$11-2026)/4 -> 266.25 | I12: =Inputs!$E$28+(Inputs!$E$27*Inputs!$E$26-Inputs!$E$28)*(I$11-2026)/4 -> 310.5
A13: IT capacity above Status quo | B13: MW IT | C13: =MAX(0,C12-C5) -> 0 | D13: =MAX(0,D12-D5) -> 37 | E13: =MAX(0,E12-E5) -> 74 | F13: =MAX(0,F12-F5) -> 111 | G13: =MAX(0,G12-G5) -> 148 | H13: =MAX(0,H12-H5) -> 185 | I13: =MAX(0,I12-I5) -> 222
A14: Hub load on the grid at the evening peak | B14: MW | C14: =C13*Inputs!$E$29*Inputs!$E$30 -> 0 | D14: =D13*Inputs!$E$29*Inputs!$E$30 -> 38.85 | E14: =E13*Inputs!$E$29*Inputs!$E$30 -> 77.7 | F14: =F13*Inputs!$E$29*Inputs!$E$30 -> 116.55 | G14: =G13*Inputs!$E$29*Inputs!$E$30 -> 155.4 | H14: =H13*Inputs!$E$29*Inputs!$E$30 -> 194.25 | I14: =I13*Inputs!$E$29*Inputs!$E$30 -> 233.1
A15: Infrastructure-fee revenue pool (Base fee) | B15: $m/yr | C15: =C12*Inputs!$E$30*Inputs!$E$32*12/1000 -> 60.75 | D15: =D12*Inputs!$E$30*Inputs!$E$32*12/1000 -> 120.4875 | E15: =E12*Inputs!$E$30*Inputs!$E$32*12/1000 -> 180.225 | F15: =F12*Inputs!$E$30*Inputs!$E$32*12/1000 -> 239.9625 | G15: =G12*Inputs!$E$30*Inputs!$E$32*12/1000 -> 299.7 | H15: =H12*Inputs!$E$30*Inputs!$E$32*12/1000 -> 359.4375 | I15: =I12*Inputs!$E$30*Inputs!$E$32*12/1000 -> 419.175
A16: Cumulative build investment since 2026 (Base cost) | B16: $m | C16: =(C12-Inputs!$E$28)*Inputs!$E$33 -> 0 | D16: =(D12-Inputs!$E$28)*Inputs!$E$33 -> 354 | E16: =(E12-Inputs!$E$28)*Inputs!$E$33 -> 708 | F16: =(F12-Inputs!$E$28)*Inputs!$E$33 -> 1062 | G16: =(G12-Inputs!$E$28)*Inputs!$E$33 -> 1416 | H16: =(H12-Inputs!$E$28)*Inputs!$E$33 -> 1770 | I16: =(I12-Inputs!$E$28)*Inputs!$E$33 -> 2124
A18: Ambitious hub | B18: Unit | C18: 2026 | D18: 2027 | E18: 2028 | F18: 2029 | G18: 2030 | H18: 2031 | I18: 2032
A19: Kenya data-centre IT capacity | B19: MW IT | C19: =Inputs!$F$28+(Inputs!$F$27*Inputs!$F$26-Inputs!$F$28)*(C$18-2026)/4 -> 45 | D19: =Inputs!$F$28+(Inputs!$F$27*Inputs!$F$26-Inputs!$F$28)*(D$18-2026)/4 -> 126.25 | E19: =Inputs!$F$28+(Inputs!$F$27*Inputs!$F$26-Inputs!$F$28)*(E$18-2026)/4 -> 207.5 | F19: =Inputs!$F$28+(Inputs!$F$27*Inputs!$F$26-Inputs!$F$28)*(F$18-2026)/4 -> 288.75 | G19: =Inputs!$F$28+(Inputs!$F$27*Inputs!$F$26-Inputs!$F$28)*(G$18-2026)/4 -> 370 | H19: =Inputs!$F$28+(Inputs!$F$27*Inputs!$F$26-Inputs!$F$28)*(H$18-2026)/4 -> 451.25 | I19: =Inputs!$F$28+(Inputs!$F$27*Inputs!$F$26-Inputs!$F$28)*(I$18-2026)/4 -> 532.5
A20: IT capacity above Status quo | B20: MW IT | C20: =MAX(0,C19-C5) -> 0 | D20: =MAX(0,D19-D5) -> 74 | E20: =MAX(0,E19-E5) -> 148 | F20: =MAX(0,F19-F5) -> 222 | G20: =MAX(0,G19-G5) -> 296 | H20: =MAX(0,H19-H5) -> 370 | I20: =MAX(0,I19-I5) -> 444
A21: Hub load on the grid at the evening peak | B21: MW | C21: =C20*Inputs!$F$29*Inputs!$F$30 -> 0 | D21: =D20*Inputs!$F$29*Inputs!$F$30 -> 77.7 | E21: =E20*Inputs!$F$29*Inputs!$F$30 -> 155.4 | F21: =F20*Inputs!$F$29*Inputs!$F$30 -> 233.1 | G21: =G20*Inputs!$F$29*Inputs!$F$30 -> 310.8 | H21: =H20*Inputs!$F$29*Inputs!$F$30 -> 388.5 | I21: =I20*Inputs!$F$29*Inputs!$F$30 -> 466.2
A22: Infrastructure-fee revenue pool (Base fee) | B22: $m/yr | C22: =C19*Inputs!$E$30*Inputs!$E$32*12/1000 -> 60.75 | D22: =D19*Inputs!$E$30*Inputs!$E$32*12/1000 -> 170.4375 | E22: =E19*Inputs!$E$30*Inputs!$E$32*12/1000 -> 280.125 | F22: =F19*Inputs!$E$30*Inputs!$E$32*12/1000 -> 389.8125 | G22: =G19*Inputs!$E$30*Inputs!$E$32*12/1000 -> 499.5 | H22: =H19*Inputs!$E$30*Inputs!$E$32*12/1000 -> 609.1875 | I22: =I19*Inputs!$E$30*Inputs!$E$32*12/1000 -> 718.875
A23: Cumulative build investment since 2026 (Base cost) | B23: $m | C23: =(C19-Inputs!$E$28)*Inputs!$E$33 -> 0 | D23: =(D19-Inputs!$E$28)*Inputs!$E$33 -> 650 | E23: =(E19-Inputs!$E$28)*Inputs!$E$33 -> 1300 | F23: =(F19-Inputs!$E$28)*Inputs!$E$33 -> 1950 | G23: =(G19-Inputs!$E$28)*Inputs!$E$33 -> 2600 | H23: =(H19-Inputs!$E$28)*Inputs!$E$33 -> 3250 | I23: =(I19-Inputs!$E$28)*Inputs!$E$33 -> 3900
A25: 2030 prize and cost, by hub case | B25: Unit | C25: Status quo | D25: Targeted hub | E25: Ambitious hub
A26: Kenya IT capacity in 2030 | B26: MW IT | C26: =G5 -> 74 | D26: =G12 -> 222 | E26: =G19 -> 370
A27: Share of Africa capacity in 2030 | B27: % | C27: =C26/Inputs!$E$26 -> 0.04 | D27: =D26/Inputs!$E$26 -> 0.12 | E27: =E26/Inputs!$E$26 -> 0.2
A28: Infrastructure-fee revenue pool, 2030 | B28: $m/yr | C28: =G8 -> 99.9 | D28: =G15 -> 299.7 | E28: =G22 -> 499.5
A29: Build investment 2026-2030 | B29: $bn | C29: =G9/1000 -> 0.232 | D29: =G16/1000 -> 1.416 | E29: =G23/1000 -> 2.6
A30: Campuses at average size | B30: count | C30: =C26/Inputs!$E$34 -> 2.1142857 | D30: =D26/Inputs!$E$34 -> 6.3428571 | E30: =E26/Inputs!$E$34 -> 10.571429
A31: Operational jobs (base jobs per campus) | B31: jobs | C31: =C30*Inputs!$E$35 -> 317.14286 | D31: =D30*Inputs!$E$35 -> 951.42857 | E31: =E30*Inputs!$E$35 -> 1585.7143
A32: Hub load added to the grid, 2030 | B32: MW | C32: =G7 -> 0 | D32: =G14 -> 155.4 | E32: =G21 -> 310.8
A33: Cost to firm 1 MW of evening peak with 4-hour storage | B33: $ per MW-yr | C33: =Inputs!$E$40*365*(Inputs!$E$38*Inputs!$E$39+(1/Inputs!$E$41-1)*Inputs!$E$42) -> 188855.29 | D33: =Inputs!$E$40*365*(Inputs!$E$38*Inputs!$E$39+(1/Inputs!$E$41-1)*Inputs!$E$42) -> 188855.29 | E33: =Inputs!$E$40*365*(Inputs!$E$38*Inputs!$E$39+(1/Inputs!$E$41-1)*Inputs!$E$42) -> 188855.29
A34: Hub-attributable firming cost, 2030 | B34: $m/yr | C34: =C32*C33/1000000 -> 0 | D34: =D32*D33/1000000 -> 29.348113 | E34: =E32*E33/1000000 -> 58.696225
A35: Firming cost as % of infrastructure-fee revenue | B35: % | C35: =IF(C28=0,0,C34/C28) -> 0 | D35: =IF(D28=0,0,D34/D28) -> 0.097924967 | E35: =IF(E28=0,0,E34/E28) -> 0.11750996
A36: Energy drawn by the whole data-centre estate, 2030 | B36: TWh/yr | C36: =C26*Inputs!$E$29*Inputs!$E$30*8760/1000000 -> 0.680652 | D36: =D26*Inputs!$E$29*Inputs!$E$30*8760/1000000 -> 2.041956 | E36: =E26*Inputs!$E$29*Inputs!$E$30*8760/1000000 -> 3.40326
A37: Cross-check: projected Kenya data-centre market in 2031 (S7) | B37: $m | C37: =805 -> 805 | D37: =805 -> 805 | E37: =805 -> 805
A38: Top-down market / bottom-up fee pool (2031 vs 2030) | B38: x | C38: =IF(C28=0,0,C37/C28) -> 8.0580581 | D38: =IF(D28=0,0,D37/D28) -> 2.6860194 | E38: =IF(E28=0,0,E37/E28) -> 1.6116116

Sheet Matrix
A1: Supply scenario x hub ambition: reserve margin, firm-MW gap and connectable load
A2: Reserve margin = (firm capacity - peak - hub load) / (peak + hub load).
A4: Supply case | B4: Hub case | C4: 2026 | D4: 2027 | E4: 2028 | F4: 2029 | G4: 2030 | H4: 2031 | I4: 2032
A5: Stress | B5: Status quo | C5: =(Grid!C14-Grid!C5-Hub!C7)/(Grid!C5+Hub!C7) -> -0.015 | D5: =(Grid!D14-Grid!D5-Hub!D7)/(Grid!D5+Hub!D7) -> -0.087962963 | E5: =(Grid!E14-Grid!E5-Hub!E7)/(Grid!E5+Hub!E7) -> -0.081859693 | F5: =(Grid!F14-Grid!F5-Hub!F7)/(Grid!F5+Hub!F7) -> -0.14987009 | G5: =(Grid!G14-Grid!G5-Hub!G7)/(Grid!G5+Hub!G7) -> -0.18936499 | H5: =(Grid!H14-Grid!H5-Hub!H7)/(Grid!H5+Hub!H7) -> -0.24941203 | I5: =(Grid!I14-Grid!I5-Hub!I7)/(Grid!I5+Hub!I7) -> -0.30501114
A6: Stress | B6: Targeted hub | C6: =(Grid!C14-Grid!C5-Hub!C14)/(Grid!C5+Hub!C14) -> -0.015 | D6: =(Grid!D14-Grid!D5-Hub!D14)/(Grid!D5+Hub!D14) -> -0.10082899 | E6: =(Grid!E14-Grid!E5-Hub!E14)/(Grid!E5+Hub!E14) -> -0.10556029 | F6: =(Grid!F14-Grid!F5-Hub!F14)/(Grid!F5+Hub!F14) -> -0.18004632 | G6: =(Grid!G14-Grid!G5-Hub!G14)/(Grid!G5+Hub!G14) -> -0.22459551 | H6: =(Grid!H14-Grid!H5-Hub!H14)/(Grid!H5+Hub!H14) -> -0.28691111 | I6: =(Grid!I14-Grid!I5-Hub!I14)/(Grid!I5+Hub!I14) -> -0.34337746
A7: Stress | B7: Ambitious hub | C7: =(Grid!C14-Grid!C5-Hub!C21)/(Grid!C5+Hub!C21) -> -0.015 | D7: =(Grid!D14-Grid!D5-Hub!D21)/(Grid!D5+Hub!D21) -> -0.11333706 | E7: =(Grid!E14-Grid!E5-Hub!E21)/(Grid!E5+Hub!E21) -> -0.12806808 | F7: =(Grid!F14-Grid!F5-Hub!F21)/(Grid!F5+Hub!F21) -> -0.20815372 | G7: =(Grid!G14-Grid!G5-Hub!G21)/(Grid!G5+Hub!G21) -> -0.2568913 | H7: =(Grid!H14-Grid!H5-Hub!H21)/(Grid!H5+Hub!H21) -> -0.3208416 | I7: =(Grid!I14-Grid!I5-Hub!I21)/(Grid!I5+Hub!I21) -> -0.37772944
A8: Base | B8: Status quo | C8: =(Grid!C29-Grid!C20-Hub!C7)/(Grid!C20+Hub!C7) -> 0.0334 | D8: =(Grid!D29-Grid!D20-Hub!D7)/(Grid!D20+Hub!D7) -> 0.088353147 | E8: =(Grid!E29-Grid!E20-Hub!E7)/(Grid!E20+Hub!E7) -> 0.021927838 | F8: =(Grid!F29-Grid!F20-Hub!F7)/(Grid!F20+Hub!F7) -> -0.01400091 | G8: =(Grid!G29-Grid!G20-Hub!G7)/(Grid!G20+Hub!G7) -> -0.027799598 | H8: =(Grid!H29-Grid!H20-Hub!H7)/(Grid!H20+Hub!H7) -> -0.043586797 | I8: =(Grid!I29-Grid!I20-Hub!I7)/(Grid!I20+Hub!I7) -> -0.061068377
A9: Base | B9: Targeted hub | C9: =(Grid!C29-Grid!C20-Hub!C14)/(Grid!C20+Hub!C14) -> 0.0334 | D9: =(Grid!D29-Grid!D20-Hub!D14)/(Grid!D20+Hub!D14) -> 0.072786699 | E9: =(Grid!E29-Grid!E20-Hub!E14)/(Grid!E20+Hub!E14) -> -0.0051803743 | F9: =(Grid!F29-Grid!F20-Hub!F14)/(Grid!F20+Hub!F14) -> -0.050444288 | G9: =(Grid!G29-Grid!G20-Hub!G14)/(Grid!G20+Hub!G14) -> -0.072371523 | H9: =(Grid!H29-Grid!H20-Hub!H14)/(Grid!H20+Hub!H14) -> -0.094645122 | I9: =(Grid!I29-Grid!I20-Hub!I14)/(Grid!I20+Hub!I14) -> -0.11716769
A10: Base | B10: Ambitious hub | C10: =(Grid!C29-Grid!C20-Hub!C21)/(Grid!C20+Hub!C21) -> 0.0334 | D10: =(Grid!D29-Grid!D20-Hub!D21)/(Grid!D20+Hub!D21) -> 0.057659259 | E10: =(Grid!E29-Grid!E20-Hub!E21)/(Grid!E20+Hub!E21) -> -0.030887576 | F10: =(Grid!F29-Grid!F20-Hub!F21)/(Grid!F20+Hub!F21) -> -0.084289731 | G10: =(Grid!G29-Grid!G20-Hub!G21)/(Grid!G20+Hub!G21) -> -0.11303568 | H10: =(Grid!H29-Grid!H20-Hub!H21)/(Grid!H20+Hub!H21) -> -0.14052821 | I10: =(Grid!I29-Grid!I20-Hub!I21)/(Grid!I20+Hub!I21) -> -0.16694131
A11: Favourable | B11: Status quo | C11: =(Grid!C44-Grid!C35-Hub!C7)/(Grid!C35+Hub!C7) -> 0.2073 | D11: =(Grid!D44-Grid!D35-Hub!D7)/(Grid!D35+Hub!D7) -> 0.2695201 | E11: =(Grid!E44-Grid!E35-Hub!E7)/(Grid!E35+Hub!E7) -> 0.23803831 | F11: =(Grid!F44-Grid!F35-Hub!F7)/(Grid!F35+Hub!F7) -> 0.21344518 | G11: =(Grid!G44-Grid!G35-Hub!G7)/(Grid!G35+Hub!G7) -> 0.2538366 | H11: =(Grid!H44-Grid!H35-Hub!H7)/(Grid!H35+Hub!H7) -> 0.28762964 | I11: =(Grid!I44-Grid!I35-Hub!I7)/(Grid!I35+Hub!I7) -> 0.31536112
A12: Favourable | B12: Targeted hub | C12: =(Grid!C44-Grid!C35-Hub!C14)/(Grid!C35+Hub!C14) -> 0.2073 | D12: =(Grid!D44-Grid!D35-Hub!D14)/(Grid!D35+Hub!D14) -> 0.25110683 | E12: =(Grid!E44-Grid!E35-Hub!E14)/(Grid!E35+Hub!E14) -> 0.20427819 | F12: =(Grid!F44-Grid!F35-Hub!F14)/(Grid!F35+Hub!F14) -> 0.16672054 | G12: =(Grid!G44-Grid!G35-Hub!G14)/(Grid!G35+Hub!G14) -> 0.1931592 | H12: =(Grid!H44-Grid!H35-Hub!H14)/(Grid!H35+Hub!H14) -> 0.21412533 | I12: =(Grid!I44-Grid!I35-Hub!I14)/(Grid!I35+Hub!I14) -> 0.23024115
A13: Favourable | B13: Ambitious hub | C13: =(Grid!C44-Grid!C35-Hub!C21)/(Grid!C35+Hub!C21) -> 0.2073 | D13: =(Grid!D44-Grid!D35-Hub!D21)/(Grid!D35+Hub!D21) -> 0.23322006 | E13: =(Grid!E44-Grid!E35-Hub!E21)/(Grid!E35+Hub!E21) -> 0.1723104 | F13: =(Grid!F44-Grid!F35-Hub!F21)/(Grid!F35+Hub!F21) -> 0.12346082 | G13: =(Grid!G44-Grid!G35-Hub!G21)/(Grid!G35+Hub!G21) -> 0.13808349 | H13: =(Grid!H44-Grid!H35-Hub!H21)/(Grid!H35+Hub!H21) -> 0.14855982 | I13: =(Grid!I44-Grid!I35-Hub!I21)/(Grid!I35+Hub!I21) -> 0.15546821
A15: Reserve margin in 2030 | B15: Supply case \ Hub case | C15: Status quo | D15: Targeted hub | E15: Ambitious hub
B16: Stress | C16: =G5 -> -0.18936499 | D16: =G6 -> -0.22459551 | E16: =G7 -> -0.2568913
B17: Base | C17: =G8 -> -0.027799598 | D17: =G9 -> -0.072371523 | E17: =G10 -> -0.11303568
B18: Favourable | C18: =G11 -> 0.2538366 | D18: =G12 -> 0.1931592 | E18: =G13 -> 0.13808349
A20: Firm MW needed in 2030 to reach the minimum reserve margin | B20: Supply case \ Hub case | C20: Status quo | D20: Targeted hub | E20: Ambitious hub
B21: Stress | C21: =MAX(0,(1+Inputs!$E$43)*(Grid!G5+Hub!G7)-Grid!G14) -> 989.70617 | D21: =MAX(0,(1+Inputs!$E$43)*(Grid!G5+Hub!G14)-Grid!G14) -> 1160.6462 | E21: =MAX(0,(1+Inputs!$E$43)*(Grid!G5+Hub!G21)-Grid!G14) -> 1331.5862
B22: Base | C22: =MAX(0,(1+Inputs!$E$43)*(Grid!G20+Hub!G7)-Grid!G29) -> 413.32645 | D22: =MAX(0,(1+Inputs!$E$43)*(Grid!G20+Hub!G14)-Grid!G29) -> 584.26645 | E22: =MAX(0,(1+Inputs!$E$43)*(Grid!G20+Hub!G21)-Grid!G29) -> 755.20645
B23: Favourable | C23: =MAX(0,(1+Inputs!$E$43)*(Grid!G35+Hub!G7)-Grid!G44) -> 0 | D23: =MAX(0,(1+Inputs!$E$43)*(Grid!G35+Hub!G14)-Grid!G44) -> 0 | E23: =MAX(0,(1+Inputs!$E$43)*(Grid!G35+Hub!G21)-Grid!G44) -> 0
A25: Firm MW needed in 2030 to reach the target reserve margin | B25: Supply case \ Hub case | C25: Status quo | D25: Targeted hub | E25: Ambitious hub
B26: Stress | C26: =MAX(0,(1+Inputs!$E$44)*(Grid!G5+Hub!G7)-Grid!G14) -> 1160.7196 | D26: =MAX(0,(1+Inputs!$E$44)*(Grid!G5+Hub!G14)-Grid!G14) -> 1339.4296 | E26: =MAX(0,(1+Inputs!$E$44)*(Grid!G5+Hub!G21)-Grid!G14) -> 1518.1396
B27: Base | C27: =MAX(0,(1+Inputs!$E$44)*(Grid!G20+Hub!G7)-Grid!G29) -> 575.03527 | D27: =MAX(0,(1+Inputs!$E$44)*(Grid!G20+Hub!G14)-Grid!G29) -> 753.74527 | E27: =MAX(0,(1+Inputs!$E$44)*(Grid!G20+Hub!G21)-Grid!G29) -> 932.45527
B28: Favourable | C28: =MAX(0,(1+Inputs!$E$44)*(Grid!G35+Hub!G7)-Grid!G44) -> 0 | D28: =MAX(0,(1+Inputs!$E$44)*(Grid!G35+Hub!G14)-Grid!G44) -> 0 | E28: =MAX(0,(1+Inputs!$E$44)*(Grid!G35+Hub!G21)-Grid!G44) -> 40.117919
A30: Storage (MWh, 4-hour) to carry the hub's own evening load in 2030 | B30: Supply case \ Hub case | C30: Status quo | D30: Targeted hub | E30: Ambitious hub
B31: Stress | C31: =Hub!G7*Inputs!$E$40 -> 0 | D31: =Hub!G14*Inputs!$E$40 -> 621.6 | E31: =Hub!G21*Inputs!$E$40 -> 1243.2
B32: Base | C32: =Hub!G7*Inputs!$E$40 -> 0 | D32: =Hub!G14*Inputs!$E$40 -> 621.6 | E32: =Hub!G21*Inputs!$E$40 -> 1243.2
B33: Favourable | C33: =Hub!G7*Inputs!$E$40 -> 0 | D33: =Hub!G14*Inputs!$E$40 -> 621.6 | E33: =Hub!G21*Inputs!$E$40 -> 1243.2
A35: Connectable new data-centre IT capacity (MW) while keeping the minimum reserve margin | B35: Supply case | C35: 2026 | D35: 2027 | E35: 2028 | F35: 2029 | G35: 2030 | H35: 2031 | I35: 2032
B36: Stress | C36: =MAX(0,(Grid!C14/(1+Inputs!$E$43)-Grid!C5)/(Inputs!$E$29*Inputs!$E$30)) -> 0 | D36: =MAX(0,(Grid!D14/(1+Inputs!$E$43)-Grid!D5)/(Inputs!$E$29*Inputs!$E$30)) -> 0 | E36: =MAX(0,(Grid!E14/(1+Inputs!$E$43)-Grid!E5)/(Inputs!$E$29*Inputs!$E$30)) -> 0 | F36: =MAX(0,(Grid!F14/(1+Inputs!$E$43)-Grid!F5)/(Inputs!$E$29*Inputs!$E$30)) -> 0 | G36: =MAX(0,(Grid!G14/(1+Inputs!$E$43)-Grid!G5)/(Inputs!$E$29*Inputs!$E$30)) -> 0 | H36: =MAX(0,(Grid!H14/(1+Inputs!$E$43)-Grid!H5)/(Inputs!$E$29*Inputs!$E$30)) -> 0 | I36: =MAX(0,(Grid!I14/(1+Inputs!$E$43)-Grid!I5)/(Inputs!$E$29*Inputs!$E$30)) -> 0
B37: Base | C37: =MAX(0,(Grid!C29/(1+Inputs!$E$43)-Grid!C20)/(Inputs!$E$29*Inputs!$E$30)) -> 0 | D37: =MAX(0,(Grid!D29/(1+Inputs!$E$43)-Grid!D20)/(Inputs!$E$29*Inputs!$E$30)) -> 0 | E37: =MAX(0,(Grid!E29/(1+Inputs!$E$43)-Grid!E20)/(Inputs!$E$29*Inputs!$E$30)) -> 0 | F37: =MAX(0,(Grid!F29/(1+Inputs!$E$43)-Grid!F20)/(Inputs!$E$29*Inputs!$E$30)) -> 0 | G37: =MAX(0,(Grid!G29/(1+Inputs!$E$43)-Grid!G20)/(Inputs!$E$29*Inputs!$E$30)) -> 0 | H37: =MAX(0,(Grid!H29/(1+Inputs!$E$43)-Grid!H20)/(Inputs!$E$29*Inputs!$E$30)) -> 0 | I37: =MAX(0,(Grid!I29/(1+Inputs!$E$43)-Grid!I20)/(Inputs!$E$29*Inputs!$E$30)) -> 0
B38: Favourable | C38: =MAX(0,(Grid!C44/(1+Inputs!$E$43)-Grid!C35)/(Inputs!$E$29*Inputs!$E$30)) -> 233.55169 | D38: =MAX(0,(Grid!D44/(1+Inputs!$E$43)-Grid!D35)/(Inputs!$E$29*Inputs!$E$30)) -> 387.43048 | E38: =MAX(0,(Grid!E44/(1+Inputs!$E$43)-Grid!E35)/(Inputs!$E$29*Inputs!$E$30)) -> 331.25429 | F38: =MAX(0,(Grid!F44/(1+Inputs!$E$43)-Grid!F35)/(Inputs!$E$29*Inputs!$E$30)) -> 285.84937 | G38: =MAX(0,(Grid!G44/(1+Inputs!$E$43)-Grid!G35)/(Inputs!$E$29*Inputs!$E$30)) -> 407.00538 | H38: =MAX(0,(Grid!H44/(1+Inputs!$E$43)-Grid!H35)/(Inputs!$E$29*Inputs!$E$30)) -> 521.23218 | I38: =MAX(0,(Grid!I44/(1+Inputs!$E$43)-Grid!I35)/(Inputs!$E$29*Inputs!$E$30)) -> 628.1833
A40: Connectable new data-centre IT capacity (MW) at the target reserve margin | B40: Supply case | C40: 2026 | D40: 2027 | E40: 2028 | F40: 2029 | G40: 2030 | H40: 2031 | I40: 2032
B41: Stress | C41: =MAX(0,(Grid!C14/(1+Inputs!$E$44)-Grid!C5)/(Inputs!$E$29*Inputs!$E$30)) -> 0 | D41: =MAX(0,(Grid!D14/(1+Inputs!$E$44)-Grid!D5)/(Inputs!$E$29*Inputs!$E$30)) -> 0 | E41: =MAX(0,(Grid!E14/(1+Inputs!$E$44)-Grid!E5)/(Inputs!$E$29*Inputs!$E$30)) -> 0 | F41: =MAX(0,(Grid!F14/(1+Inputs!$E$44)-Grid!F5)/(Inputs!$E$29*Inputs!$E$30)) -> 0 | G41: =MAX(0,(Grid!G14/(1+Inputs!$E$44)-Grid!G5)/(Inputs!$E$29*Inputs!$E$30)) -> 0 | H41: =MAX(0,(Grid!H14/(1+Inputs!$E$44)-Grid!H5)/(Inputs!$E$29*Inputs!$E$30)) -> 0 | I41: =MAX(0,(Grid!I14/(1+Inputs!$E$44)-Grid!I5)/(Inputs!$E$29*Inputs!$E$30)) -> 0
B42: Base | C42: =MAX(0,(Grid!C29/(1+Inputs!$E$44)-Grid!C20)/(Inputs!$E$29*Inputs!$E$30)) -> 0 | D42: =MAX(0,(Grid!D29/(1+Inputs!$E$44)-Grid!D20)/(Inputs!$E$29*Inputs!$E$30)) -> 0 | E42: =MAX(0,(Grid!E29/(1+Inputs!$E$44)-Grid!E20)/(Inputs!$E$29*Inputs!$E$30)) -> 0 | F42: =MAX(0,(Grid!F29/(1+Inputs!$E$44)-Grid!F20)/(Inputs!$E$29*Inputs!$E$30)) -> 0 | G42: =MAX(0,(Grid!G29/(1+Inputs!$E$44)-Grid!G20)/(Inputs!$E$29*Inputs!$E$30)) -> 0 | H42: =MAX(0,(Grid!H29/(1+Inputs!$E$44)-Grid!H20)/(Inputs!$E$29*Inputs!$E$30)) -> 0 | I42: =MAX(0,(Grid!I29/(1+Inputs!$E$44)-Grid!I20)/(Inputs!$E$29*Inputs!$E$30)) -> 0
B43: Favourable | C43: =MAX(0,(Grid!C44/(1+Inputs!$E$44)-Grid!C35)/(Inputs!$E$29*Inputs!$E$30)) -> 119.29789 | D43: =MAX(0,(Grid!D44/(1+Inputs!$E$44)-Grid!D35)/(Inputs!$E$29*Inputs!$E$30)) -> 261.28133 | E43: =MAX(0,(Grid!E44/(1+Inputs!$E$44)-Grid!E35)/(Inputs!$E$29*Inputs!$E$30)) -> 202.08236 | F43: =MAX(0,(Grid!F44/(1+Inputs!$E$44)-Grid!F35)/(Inputs!$E$29*Inputs!$E$30)) -> 152.9131 | G43: =MAX(0,(Grid!G44/(1+Inputs!$E$44)-Grid!G35)/(Inputs!$E$29*Inputs!$E$30)) -> 262.77605 | H43: =MAX(0,(Grid!H44/(1+Inputs!$E$44)-Grid!H35)/(Inputs!$E$29*Inputs!$E$30)) -> 365.70979 | I43: =MAX(0,(Grid!I44/(1+Inputs!$E$44)-Grid!I35)/(Inputs!$E$29*Inputs!$E$30)) -> 461.36786

Sheet UnitEconomics
A1: Unit economics: what a tenant pays, and whether a reference campus clears its hurdle
A2: Part 1 is a tenant's all-in cost per IT kW-month. Part 2 is an illustrative pre-tax, unlevered campus case; every driver is an input.
A4: Part 1. Tenant cost per IT kW-month | B4: Unit | C4: Stress | D4: Base | E4: Favourable | F4: Ethiopia-linked benchmark
A5: Infrastructure fee | B5: $/kW-month | C5: =Inputs!$D$32 -> 110 | D5: =Inputs!$E$32 -> 150 | E5: =Inputs!$F$32 -> 200 | F5: =Inputs!$E$32 -> 150
A6: Grid power (PUE x 730 h x all-in tariff) | B6: $/kW-month | C6: =Inputs!$D$29*730*Inputs!$D$36 -> 112.42 | D6: =Inputs!$E$29*730*Inputs!$E$36 -> 91.98 | E6: =Inputs!$F$29*730*Inputs!$F$36 -> 66.43 | F6: =Inputs!$E$29*730*Inputs!$E$37 -> 66.43
A7: Evening self-supply premium (storage shifting cost, per IT kW) | B7: $/kW-month | C7: =Inputs!$D$29*Inputs!$D$40*365/12*(Inputs!$D$38*Inputs!$D$39+(1/Inputs!$D$41-1)*Inputs!$D$42)/1000 -> 22.033118 | D7: =Inputs!$E$29*Inputs!$E$40*365/12*(Inputs!$E$38*Inputs!$E$39+(1/Inputs!$E$41-1)*Inputs!$E$42)/1000 -> 22.033118 | E7: =Inputs!$F$29*Inputs!$F$40*365/12*(Inputs!$F$38*Inputs!$F$39+(1/Inputs!$F$41-1)*Inputs!$F$42)/1000 -> 22.033118 | F7: =Inputs!$E$29*Inputs!$E$40*365/12*(Inputs!$E$38*Inputs!$E$39+(1/Inputs!$E$41-1)*Inputs!$E$42)/1000 -> 22.033118
A8: All-in tenant cost | B8: $/kW-month | C8: =SUM(C5:C7) -> 244.45312 | D8: =SUM(D5:D7) -> 264.01312 | E8: =SUM(E5:E7) -> 288.46312 | F8: =SUM(F5:F7) -> 238.46312
A9: Power (grid + evening premium) as % of all-in cost | B9: % | C9: =(C6+C7)/C8 -> 0.55001597 | D9: =(D6+D7)/D8 -> 0.43184641 | E9: =(E6+E7)/E8 -> 0.30667046 | F9: =(F6+F7)/F8 -> 0.37097191
A10: Power-price gap to the Ethiopia-linked benchmark (grid power only) | B10: $/kW-month | C10: =C6-$F$6 -> 45.99 | D10: =D6-$F$6 -> 25.55 | E10: =E6-$F$6 -> 0
A11: ...as % of the tenant's all-in cost | B11: % | C11: =C10/C8 -> 0.18813423 | D11: =D10/D8 -> 0.096775494 | E11: =E10/E8 -> 0
A13: Part 2. Reference campus cash flow (Base case, $m unless stated) | B13: Unit | C13: t=0 | D13: t=1 | E13: t=2 | F13: t=3 | G13: t=4 | H13: t=5 | I13: t=6 | J13: t=7 | K13: t=8 | L13: t=9 | M13: t=10 | N13: t=11
A14: Period index t | C14: 0 | D14: 1 | E14: 2 | F14: 3 | G14: 4 | H14: 5 | I14: 6 | J14: 7 | K14: 8 | L14: 9 | M14: 10 | N14: 11
A15: Calendar year | C15: =Inputs!$E$54+C14 -> 2027 | D15: =Inputs!$E$54+D14 -> 2028 | E15: =Inputs!$E$54+E14 -> 2029 | F15: =Inputs!$E$54+F14 -> 2030 | G15: =Inputs!$E$54+G14 -> 2031 | H15: =Inputs!$E$54+H14 -> 2032 | I15: =Inputs!$E$54+I14 -> 2033 | J15: =Inputs!$E$54+J14 -> 2034 | ... N15: =Inputs!$E$54+N14 -> 2038
A16: Installed IT capacity | B16: MW | C16: =Inputs!$E$46+IF(C14>=Inputs!$E$48,Inputs!$E$47,0) -> 22 | D16: =Inputs!$E$46+IF(D14>=Inputs!$E$48,Inputs!$E$47,0) -> 22 | E16: =Inputs!$E$46+IF(E14>=Inputs!$E$48,Inputs!$E$47,0) -> 44 | F16: =Inputs!$E$46+IF(F14>=Inputs!$E$48,Inputs!$E$47,0) -> 44 | G16: =Inputs!$E$46+IF(G14>=Inputs!$E$48,Inputs!$E$47,0) -> 44 | H16: =Inputs!$E$46+IF(H14>=Inputs!$E$48,Inputs!$E$47,0) -> 44 | I16: =Inputs!$E$46+IF(I14>=Inputs!$E$48,Inputs!$E$47,0) -> 44 | J16: =Inputs!$E$46+IF(J14>=Inputs!$E$48,Inputs!$E$47,0) -> 44 | ... N16: =Inputs!$E$46+IF(N14>=Inputs!$E$48,Inputs!$E$47,0) -> 44
A17: Contracted IT load (input ramp) | B17: MW | C17: 8 | D17: 15 | E17: 22 | F17: 28 | G17: 33 | H17: 33 | I17: 33 | J17: 33 | K17: 33 | L17: 33 | M17: 33 | N17: 33
A18: Contracted IT load (capped at installed) | B18: MW | C18: =MIN(C17,C16) -> 8 | D18: =MIN(D17,D16) -> 15 | E18: =MIN(E17,E16) -> 22 | F18: =MIN(F17,F16) -> 28 | G18: =MIN(G17,G16) -> 33 | H18: =MIN(H17,H16) -> 33 | I18: =MIN(I17,I16) -> 33 | J18: =MIN(J17,J16) -> 33 | ... N18: =MIN(N17,N16) -> 33
A19: Infrastructure-fee revenue | B19: $m | C19: =C18*Inputs!$E$32*12/1000 -> 14.4 | D19: =D18*Inputs!$E$32*12/1000 -> 27 | E19: =E18*Inputs!$E$32*12/1000 -> 39.6 | F19: =F18*Inputs!$E$32*12/1000 -> 50.4 | G19: =G18*Inputs!$E$32*12/1000 -> 59.4 | H19: =H18*Inputs!$E$32*12/1000 -> 59.4 | I19: =I18*Inputs!$E$32*12/1000 -> 59.4 | J19: =J18*Inputs!$E$32*12/1000 -> 59.4 | ... N19: =N18*Inputs!$E$32*12/1000 -> 59.4
A20: Variable opex | B20: $m | C20: =-C19*Inputs!$E$50 -> -2.88 | D20: =-D19*Inputs!$E$50 -> -5.4 | E20: =-E19*Inputs!$E$50 -> -7.92 | F20: =-F19*Inputs!$E$50 -> -10.08 | G20: =-G19*Inputs!$E$50 -> -11.88 | H20: =-H19*Inputs!$E$50 -> -11.88 | I20: =-I19*Inputs!$E$50 -> -11.88 | J20: =-J19*Inputs!$E$50 -> -11.88 | ... N20: =-N19*Inputs!$E$50 -> -11.88
A21: Fixed opex | B21: $m | C21: =-C16*Inputs!$E$51 -> -3.3 | D21: =-D16*Inputs!$E$51 -> -3.3 | E21: =-E16*Inputs!$E$51 -> -6.6 | F21: =-F16*Inputs!$E$51 -> -6.6 | G21: =-G16*Inputs!$E$51 -> -6.6 | H21: =-H16*Inputs!$E$51 -> -6.6 | I21: =-I16*Inputs!$E$51 -> -6.6 | J21: =-J16*Inputs!$E$51 -> -6.6 | ... N21: =-N16*Inputs!$E$51 -> -6.6
A22: EBITDA | B22: $m | C22: =C19+C20+C21 -> 8.22 | D22: =D19+D20+D21 -> 18.3 | E22: =E19+E20+E21 -> 25.08 | F22: =F19+F20+F21 -> 33.72 | G22: =G19+G20+G21 -> 40.92 | H22: =H19+H20+H21 -> 40.92 | I22: =I19+I20+I21 -> 40.92 | J22: =J19+J20+J21 -> 40.92 | ... N22: =N19+N20+N21 -> 40.92
A23: Growth capacity added (MW) | B23: MW | C23: =IF(C14=0,Inputs!$E$46,0)+IF(C14=Inputs!$E$48,Inputs!$E$47,0) -> 22 | D23: =IF(D14=0,Inputs!$E$46,0)+IF(D14=Inputs!$E$48,Inputs!$E$47,0) -> 0 | E23: =IF(E14=0,Inputs!$E$46,0)+IF(E14=Inputs!$E$48,Inputs!$E$47,0) -> 22 | F23: =IF(F14=0,Inputs!$E$46,0)+IF(F14=Inputs!$E$48,Inputs!$E$47,0) -> 0 | G23: =IF(G14=0,Inputs!$E$46,0)+IF(G14=Inputs!$E$48,Inputs!$E$47,0) -> 0 | H23: =IF(H14=0,Inputs!$E$46,0)+IF(H14=Inputs!$E$48,Inputs!$E$47,0) -> 0 | I23: =IF(I14=0,Inputs!$E$46,0)+IF(I14=Inputs!$E$48,Inputs!$E$47,0) -> 0 | J23: =IF(J14=0,Inputs!$E$46,0)+IF(J14=Inputs!$E$48,Inputs!$E$47,0) -> 0 | ... N23: =IF(N14=0,Inputs!$E$46,0)+IF(N14=Inputs!$E$48,Inputs!$E$47,0) -> 0
A24: Growth capex | B24: $m | C24: =-C23*Inputs!$E$33 -> -176 | D24: =-D23*Inputs!$E$33 -> 0 | E24: =-E23*Inputs!$E$33 -> -176 | F24: =-F23*Inputs!$E$33 -> 0 | G24: =-G23*Inputs!$E$33 -> 0 | H24: =-H23*Inputs!$E$33 -> 0 | I24: =-I23*Inputs!$E$33 -> 0 | J24: =-J23*Inputs!$E$33 -> 0 | ... N24: =-N23*Inputs!$E$33 -> 0
A25: Cumulative growth MW at start of period | B25: MW | C25: =0 -> 0 | D25: =SUM($C23:C23) -> 22 | E25: =SUM($C23:D23) -> 22 | F25: =SUM($C23:E23) -> 44 | G25: =SUM($C23:F23) -> 44 | H25: =SUM($C23:G23) -> 44 | I25: =SUM($C23:H23) -> 44 | J25: =SUM($C23:I23) -> 44 | K25: =SUM($C23:J23) -> 44 | ... N25: =SUM($C23:M23) -> 44
A26: Maintenance capex | B26: $m | C26: =-C25*Inputs!$E$33*Inputs!$E$52 -> 0 | D26: =-D25*Inputs!$E$33*Inputs!$E$52 -> -2.64 | E26: =-E25*Inputs!$E$33*Inputs!$E$52 -> -2.64 | F26: =-F25*Inputs!$E$33*Inputs!$E$52 -> -5.28 | G26: =-G25*Inputs!$E$33*Inputs!$E$52 -> -5.28 | H26: =-H25*Inputs!$E$33*Inputs!$E$52 -> -5.28 | I26: =-I25*Inputs!$E$33*Inputs!$E$52 -> -5.28 | J26: =-J25*Inputs!$E$33*Inputs!$E$52 -> -5.28 | ... N26: =-N25*Inputs!$E$33*Inputs!$E$52 -> -5.28
A27: Terminal value (multiple of final-year EBITDA) | B27: $m | C27: =0 -> 0 | D27: =0 -> 0 | E27: =0 -> 0 | F27: =0 -> 0 | G27: =0 -> 0 | H27: =0 -> 0 | I27: =0 -> 0 | J27: =0 -> 0 | ... M27: =0 -> 0 | N27: =Inputs!$E$53*N22 -> 286.44
A28: Pre-tax unlevered cash flow | B28: $m | C28: =C22+C24+C26+C27 -> -167.78 | D28: =D22+D24+D26+D27 -> 15.66 | E28: =E22+E24+E26+E27 -> -153.56 | F28: =F22+F24+F26+F27 -> 28.44 | G28: =G22+G24+G26+G27 -> 35.64 | H28: =H22+H24+H26+H27 -> 35.64 | I28: =I22+I24+I26+I27 -> 35.64 | J28: =J22+J24+J26+J27 -> 35.64 | ... N28: =N22+N24+N26+N27 -> 322.08
A30: Linear decomposition (NPV is linear in fee and in capex per MW) | B30: Unit | C30: t=0 | D30: t=1 | E30: t=2 | F30: t=3 | G30: t=4 | H30: t=5 | I30: t=6 | J30: t=7 | K30: t=8 | L30: t=9 | M30: t=10 | N30: t=11
A31: Fee-linked cash flow per $1/kW-month of fee | B31: $m | C31: =C18*12/1000*(1-Inputs!$E$50) -> 0.0768 | D31: =D18*12/1000*(1-Inputs!$E$50) -> 0.144 | E31: =E18*12/1000*(1-Inputs!$E$50) -> 0.2112 | F31: =F18*12/1000*(1-Inputs!$E$50) -> 0.2688 | G31: =G18*12/1000*(1-Inputs!$E$50) -> 0.3168 | H31: =H18*12/1000*(1-Inputs!$E$50) -> 0.3168 | I31: =I18*12/1000*(1-Inputs!$E$50) -> 0.3168 | J31: =J18*12/1000*(1-Inputs!$E$50) -> 0.3168 | ... M31: =M18*12/1000*(1-Inputs!$E$50) -> 0.3168 | N31: =N18*12/1000*(1-Inputs!$E$50)+Inputs!$E$53*N18*12/1000*(1-Inputs!$E$50) -> 2.5344
A32: Fixed-opex cash flow (incl. terminal value effect) | B32: $m | C32: =-C16*Inputs!$E$51 -> -3.3 | D32: =-D16*Inputs!$E$51 -> -3.3 | E32: =-E16*Inputs!$E$51 -> -6.6 | F32: =-F16*Inputs!$E$51 -> -6.6 | G32: =-G16*Inputs!$E$51 -> -6.6 | H32: =-H16*Inputs!$E$51 -> -6.6 | I32: =-I16*Inputs!$E$51 -> -6.6 | J32: =-J16*Inputs!$E$51 -> -6.6 | ... M32: =-M16*Inputs!$E$51 -> -6.6 | N32: =-N16*Inputs!$E$51-Inputs!$E$53*N16*Inputs!$E$51 -> -52.8
A33: Capex cash flow per $1m of build cost per MW | B33: $m | C33: =-(C23+C25*Inputs!$E$52) -> -22 | D33: =-(D23+D25*Inputs!$E$52) -> -0.33 | E33: =-(E23+E25*Inputs!$E$52) -> -22.33 | F33: =-(F23+F25*Inputs!$E$52) -> -0.66 | G33: =-(G23+G25*Inputs!$E$52) -> -0.66 | H33: =-(H23+H25*Inputs!$E$52) -> -0.66 | I33: =-(I23+I25*Inputs!$E$52) -> -0.66 | J33: =-(J23+J25*Inputs!$E$52) -> -0.66 | ... N33: =-(N23+N25*Inputs!$E$52) -> -0.66
A35: Results (Base case) | B35: Unit | C35: Value
A36: NPV at the base discount rate | B36: $m | C36: =C28+NPV(Inputs!$E$49,D28:N28) -> -15.837293
A37: IRR (pre-tax, unlevered, incl. terminal value) | B37: % | C37: =IRR(C28:N28) -> 0.091361627
A38: NPV with no terminal value | B38: $m | C38: =C36-N27/(1+Inputs!$E$49)^11 -> -116.23277
A39: NPV change per +$1/kW-month of fee | B39: $m | C39: =C31+NPV(Inputs!$E$49,D31:N31) -> 2.6312639
A40: NPV excluding fee and capex effects (fixed opex) | B40: $m | C40: =C32+NPV(Inputs!$E$49,D32:N32) -> -59.360221
A41: NPV change per +$1m/MW of build cost | B41: $m | C41: =C33+NPV(Inputs!$E$49,D33:N33) -> -43.895831
A42: Break-even fee at Base build cost (NPV = 0) | B42: $/kW-month | C42: =-(C40+C41*Inputs!$E$33)/C39 -> 156.01889
A43: Check: linear decomposition reproduces NPV (should be 0) | B43: $m | C43: =ROUND(C39*Inputs!$E$32+C40+C41*Inputs!$E$33-C36,6) -> 0
A44: Stabilised EBITDA yield on build cost (final year) | B44: % | C44: =N22/(Inputs!$E$33*(Inputs!$E$46+Inputs!$E$47)) -> 0.11625
A46: NPV ($m): infrastructure fee ($/kW-month, down) x build cost ($m per MW, across) | B46: Fee \ Build cost
C47: 6 | D47: 7 | E47: 8 | F47: 9 | G47: 10 | H47: 11.3
B48: 110 | C48: =$C$39*$B48+$C$40+$C$41*C$47 -> -33.296184 | D48: =$C$39*$B48+$C$40+$C$41*D$47 -> -77.192015 | E48: =$C$39*$B48+$C$40+$C$41*E$47 -> -121.08785 | F48: =$C$39*$B48+$C$40+$C$41*F$47 -> -164.98368 | G48: =$C$39*$B48+$C$40+$C$41*G$47 -> -208.87951 | H48: =$C$39*$B48+$C$40+$C$41*H$47 -> -265.94409
B49: 130 | C49: =$C$39*$B49+$C$40+$C$41*C$47 -> 19.329093 | D49: =$C$39*$B49+$C$40+$C$41*D$47 -> -24.566738 | E49: =$C$39*$B49+$C$40+$C$41*E$47 -> -68.46257 | F49: =$C$39*$B49+$C$40+$C$41*F$47 -> -112.3584 | G49: =$C$39*$B49+$C$40+$C$41*G$47 -> -156.25423 | H49: =$C$39*$B49+$C$40+$C$41*H$47 -> -213.31881
B50: 150 | C50: =$C$39*$B50+$C$40+$C$41*C$47 -> 71.95437 | D50: =$C$39*$B50+$C$40+$C$41*D$47 -> 28.058539 | E50: =$C$39*$B50+$C$40+$C$41*E$47 -> -15.837293 | F50: =$C$39*$B50+$C$40+$C$41*F$47 -> -59.733124 | G50: =$C$39*$B50+$C$40+$C$41*G$47 -> -103.62895 | H50: =$C$39*$B50+$C$40+$C$41*H$47 -> -160.69354
B51: 175 | C51: =$C$39*$B51+$C$40+$C$41*C$47 -> 137.73597 | D51: =$C$39*$B51+$C$40+$C$41*D$47 -> 93.840135 | E51: =$C$39*$B51+$C$40+$C$41*E$47 -> 49.944304 | F51: =$C$39*$B51+$C$40+$C$41*F$47 -> 6.0484726 | G51: =$C$39*$B51+$C$40+$C$41*G$47 -> -37.847359 | H51: =$C$39*$B51+$C$40+$C$41*H$47 -> -94.911939
B52: 200 | C52: =$C$39*$B52+$C$40+$C$41*C$47 -> 203.51756 | D52: =$C$39*$B52+$C$40+$C$41*D$47 -> 159.62173 | E52: =$C$39*$B52+$C$40+$C$41*E$47 -> 115.7259 | F52: =$C$39*$B52+$C$40+$C$41*F$47 -> 71.830069 | G52: =$C$39*$B52+$C$40+$C$41*G$47 -> 27.934238 | H52: =$C$39*$B52+$C$40+$C$41*H$47 -> -29.130343
B53: 225 | C53: =$C$39*$B53+$C$40+$C$41*C$47 -> 269.29916 | D53: =$C$39*$B53+$C$40+$C$41*D$47 -> 225.40333 | E53: =$C$39*$B53+$C$40+$C$41*E$47 -> 181.5075 | F53: =$C$39*$B53+$C$40+$C$41*F$47 -> 137.61167 | G53: =$C$39*$B53+$C$40+$C$41*G$47 -> 93.715834 | H53: =$C$39*$B53+$C$40+$C$41*H$47 -> 36.651253
B54: Break-even fee | C54: =-($C$40+$C$41*C$47)/$C$39 -> 122.65407 | D54: =-($C$40+$C$41*D$47)/$C$39 -> 139.33648 | E54: =-($C$40+$C$41*E$47)/$C$39 -> 156.01889 | F54: =-($C$40+$C$41*F$47)/$C$39 -> 172.70131 | G54: =-($C$40+$C$41*G$47)/$C$39 -> 189.38372 | H54: =-($C$40+$C$41*H$47)/$C$39 -> 211.07086
A56: NPV ($m) at different discount rates (Base fee and build cost) | B56: Rate | C56: NPV
B57: 0.08 | C57: =$C$28+NPV(B57,$D$28:$N$28) -> 23.077795
B58: 0.1 | C58: =$C$28+NPV(B58,$D$28:$N$28) -> -15.837293
B59: 0.12 | C59: =$C$28+NPV(B59,$D$28:$N$28) -> -47.608933
B60: 0.14 | C60: =$C$28+NPV(B60,$D$28:$N$28) -> -73.637281

Sheet Levers
A1: What it would take: five levers sized against the 2030 firm-capacity gap (Base supply, Targeted hub)
A2: Costs are indicative annual procurement costs, not a budget. Lever sizes are inputs on the Inputs sheet (section F).
A4: Lever | B4: Unit | C4: Firm MW | D4: Lead time | E4: Evidence / basis | F4: Tag | G4: Indicative cost ($m/yr)
A5: 1. Data centres bring their own evening power (on-site storage) | B5: MW | C5: =Hub!D32 -> 155.4 | D5: Built with each campus (12-18 months) | E5: S2: evening peak 6-10pm; sized at the Targeted-hub load added in 2030. Cost borne by tenants. | F5: [A] | G5: =C5*Hub!D33/1000000 -> 29.348113
A6: 2. Utility-scale 4-hour storage via auctions | B6: MW | C6: =Inputs!$E$56 -> 250 | D6: 24-30 months after financial close (S14) | E6: S13 first 100 MW in 2027; S14 BESS inside the auction framework. | F6: [A] | G6: =C6*Hub!D33/1000000 -> 47.213824
A7: 3. Second Ethiopia import tranche | B7: MW | C7: =Inputs!$E$57 -> 150 | D7: 12-24 months (existing interconnector) | E7: S2 / S19: 200 MW now, 400 MW PPA cap, large Ethiopian hydro surplus. Priced at the 6.5 c/kWh PPA benchmark. | F7: [A] | G7: =C7*8.76*Inputs!$E$60*Inputs!$E$37 -> 72.5985
A8: 4. Accelerated geothermal (Olkaria VII, wellhead units) | B8: MW | C8: =Inputs!$E$58 -> 100 | D8: 12-36 months (S13: wellhead units by 2027) | E8: S13: Olkaria VII 80.3 MW; mobile wellhead units. Priced at wholesale $0.07/kWh (S15). | F8: [A] | G8: =C8*8.76*Inputs!$E$61*Inputs!$E$42/1000 -> 55.188
A9: 5. Auction tranche pulled forward one year | B9: MW | C9: =Inputs!$E$59 -> 150 | D9: Needs auction live by late 2026 (S14) | E9: S14: first COD c.2030; this lever brings one tranche to 2029. Priced at wholesale $0.07/kWh. | F9: [A] | G9: =C9*8.76*Inputs!$E$61*Inputs!$E$42/1000 -> 82.782
A10: Package total | C10: =SUM(C5:C9) -> 805.4 | G10: =SUM(G5:G9) -> 287.13044
A12: Coverage of the 2030 gap | B12: Unit | C12: Value
A13: Gap to the minimum reserve margin (Base supply, Targeted hub, 2030) | B13: MW | C13: =Matrix!D22 -> 584.26645
A14: Gap to the target reserve margin (Base supply, Targeted hub, 2030) | B14: MW | C14: =Matrix!D27 -> 753.74527
A15: Package coverage of the minimum-margin gap | B15: x | C15: =C10/C13 -> 1.3784807
A16: Package coverage of the target-margin gap | B16: x | C16: =C10/C14 -> 1.0685308
A17: Reserve margin in 2030 after the package (Base supply, Targeted hub) | B17: % | C17: =(Grid!G29+C10-Grid!G20-Hub!G14)/(Grid!G20+Hub!G14) -> 0.16523929
A18: Share of the package supplied by the data centres themselves (lever 1) | B18: % | C18: =C5/C10 -> 0.1929476
A19: Share of the target-margin gap attributable to the hub (hub load / gap) | B19: % | C19: =Hub!D32/C14 -> 0.20617045

Sheet Screen
A1: Beyond data centres: which energy-intensive industries fit Kenya's grid shape?
A2: Scores 1-5 are analyst JUDGEMENT [J], not data. Change the blue weights and scores to test the ranking; the equal-weight ranking shows how much the weights matter.
A4: Industry | B4: Fit with an evening-constrained grid (load flexibility) | C4: Market pull evidence | D4: Kenya's input advantage | E4: Jobs per MW | F4: Speed to deploy | G4: Weighted score | H4: Rank | I4: Equal-weight rank | J4: Equal-weight mean
A5: Weight | B5: 0.3 | C5: 0.2 | D5: 0.2 | E5: 0.15 | F5: 0.15 | G5: =SUM(B5:F5) -> 1
A6: Agro-processing and cold chain | B6: 4 | C6: 4 | D6: 4 | E6: 5 | F6: 5 | G6: =SUMPRODUCT($B$5:$F$5,B6:F6) -> 4.3 | H6: =RANK(G6,$G$6:$G$12) -> 1 | I6: =RANK(AVERAGE(B6:F6),$J$6:$J$12) -> 1 | J6: =AVERAGE(B6:F6) -> 4.4
A7: Night-shift heavy industry (cement, steel recycling, glass) | B7: 5 | C7: 4 | D7: 3 | E7: 4 | F7: 4 | G7: =SUMPRODUCT($B$5:$F$5,B7:F7) -> 4.1 | H7: =RANK(G7,$G$6:$G$12) -> 2 | I7: =RANK(AVERAGE(B7:F7),$J$6:$J$12) -> 2 | J7: =AVERAGE(B7:F7) -> 4
A8: Textiles and apparel in export zones | B8: 3 | C8: 3 | D8: 3 | E8: 5 | F8: 4 | G8: =SUMPRODUCT($B$5:$F$5,B8:F8) -> 3.45 | H8: =RANK(G8,$G$6:$G$12) -> 3 | I8: =RANK(AVERAGE(B8:F8),$J$6:$J$12) -> 3 | J8: =AVERAGE(B8:F8) -> 3.6
A9: Flexible / batch compute (AI training, rendering) | B9: 5 | C9: 3 | D9: 3 | E9: 1 | F9: 3 | G9: =SUMPRODUCT($B$5:$F$5,B9:F9) -> 3.3 | H9: =RANK(G9,$G$6:$G$12) -> 4 | I9: =RANK(AVERAGE(B9:F9),$J$6:$J$12) -> 6 | J9: =AVERAGE(B9:F9) -> 3
A10: EV and battery assembly, smart charging | B10: 4 | C10: 3 | D10: 3 | E10: 3 | F10: 3 | G10: =SUMPRODUCT($B$5:$F$5,B10:F10) -> 3.3 | H10: =RANK(G10,$G$6:$G$12) -> 5 | I10: =RANK(AVERAGE(B10:F10),$J$6:$J$12) -> 4 | J10: =AVERAGE(B10:F10) -> 3.2
A11: Cloud and colocation data centres | B11: 2 | C11: 5 | D11: 4 | E11: 2 | F11: 3 | G11: =SUMPRODUCT($B$5:$F$5,B11:F11) -> 3.15 | H11: =RANK(G11,$G$6:$G$12) -> 6 | I11: =RANK(AVERAGE(B11:F11),$J$6:$J$12) -> 4 | J11: =AVERAGE(B11:F11) -> 3.2
A12: Green hydrogen / ammonia (electrolysis) | B12: 5 | C12: 2 | D12: 3 | E12: 2 | F12: 1 | G12: =SUMPRODUCT($B$5:$F$5,B12:F12) -> 2.95 | H12: =RANK(G12,$G$6:$G$12) -> 7 | I12: =RANK(AVERAGE(B12:F12),$J$6:$J$12) -> 7 | J12: =AVERAGE(B12:F12) -> 2.6
A14: Why these criteria: Kenya's binding constraint is firm power at 6-10pm (S2). Loads that can move off that window, or store their own evening energy, use the grid's idle hours (night tariff uptake +74% in H2 2025, S17) instead of competing for its scarcest ones.

Sheet Sources
A1: Source register and conflicts
A2: Figures read on 2026-10-19. Press and trade-press sources: confirm against EPRA / Kenya Power primary releases before publication.
A4: ID | B4: Source | C4: Date | D4: URL | E4: What the model takes from it
A5: S1 | B5: Business Daily - Kenya risks electricity cuts as reserve shrinks to 3.3pc | C5: 2026-08-26 | D5: https://www.businessdailyafrica.com/bd/corporate/industry/kenya-risks-electricity-cuts-as-reserve-shrinks-to-3-3pc-5572288 | E5: Reserve margin below 3.3%; IEA comfortable range of 20-35%; State of the Grid briefing 11 Aug 2026
A6: S2 | B6: TechTrends KE - Kenya electricity rationing risk | C6: 2026-08-27 | D6: https://techtrendske.co.ke/2026/08/27/kenya-electricity-rationing-risk/ | E6: Peak demand series (2,177 / 2,316 / 2,514 / 2,549 MW); reserve margin 20.73% (Jan 2026) to 3.34% (Jun 2026); Ethiopia imports 200 MW expected to double; evening peak c.6-10pm; wind+solar >20% of capacity; little battery storage
A7: S3 | B7: Business Daily - How Kenya teetered on the brink of widespread power rationing | C7: 2026-09-24 | D7: https://www.businessdailyafrica.com/bd/corporate/industry/how-kenya-teetered-on-the-brink-of-widespread-power-rationing-5607180 | E7: Reserve margin of -1.5% over the 12 months to June 2026 (headline figure only; article body did not load)
A8: S4 | B8: Business Daily - Kenya electricity imports rise further to avert rationing | C8: 2026-08-30 | D8: https://www.businessdailyafrica.com/bd/corporate/industry/kenya-electricity-imports-rise-further-to-avert-rationing-5575112 | E8: Imports 12% of Kenya Power supply in H1 2026 vs 10% in H1 2025 (Ethiopia, Uganda)
A9: S5 | B9: Capital FM / AllAfrica - Kenya tops East Africa in power demand and renewables (EPRA 2025 statistics) | C9: 2025-10-23 | D9: https://capitalfm.africa/kenya-tops-east-africa-renewable-energy-generation-epra-report/ | E9: Renewable share 80.17%; geothermal 940 MW; installed capacity 3,192 MW; peak demand 2,316 MW (2025)
A10: S6 | B10: The Star - Kenya's renewable energy generation mix | C10: 2026-04-09 | D10: https://www.the-star.co.ke/news/infographics/2026-04-09-kenyas-renewable-energy-generation-mix | E10: Jul-Dec 2025 mix: geothermal 40.06%, thermal 9.11%, imports 12.10%, renewables 78.79%
A11: S7 | B11: Semafor - Energy shortfall 'problem' scuppers Kenya's $1B Microsoft data center | C11: 2026-05-06 | D11: https://semafor.com/article/05/06/2026/energy-shortfall-problem-scuppers-kenyas-1b-microsoft-data-center | E11: Microsoft/G42 Olkaria project unlikely to proceed; President Ruto: power capacity inadequate; 10,000 MW by 2030 target; Kenya DC market projected at $805m by 2031; Nxtra 44 MW at Tatu City
A12: S8 | B12: Citizen Digital - Kenya's $1B Microsoft data centre project in limbo over power concerns | C12: 2026-05-23 | D12: https://citizen.digital/article/kenyas-1b-microsoft-data-centre-project-in-limbo-over-power-concerns-n383281 | E12: Government says project not abandoned; Ruto: one data centre requires 1,000 MW; daily load-shedding 5-10pm (Nov 2025); target at least 10,000 MW by 2030, >KSh 1 trillion
A13: S9 | B13: BusinessWire / ResearchAndMarkets - Kenya Colocation Data Center Portfolio Analysis 2025 | C13: 2025-06-18 | D13: https://www.businesswire.com/news/home/20250618339125/en/Kenya-Colocation-Data-Center-Portfolio-Analysis-Report-2025-Detailed-Analysis-of-13-Existing-Data-Centers-and-9-Upcoming-Data-Centers---ResearchAndMarkets.com | E13: Existing IT capacity almost 20 MW; upcoming c.200 MW; almost 25 MW more by end-2025; 13 existing and 9 upcoming facilities
A14: S10 | B14: Connecting Africa - Airtel breaks ground on 44MW data center in Nairobi | C14: 2025-09 | D14: https://www.connectingafrica.com/data-centers/airtel-breaks-ground-on-44mw-data-center-in-nairobi | E14: Nxtra by Airtel, Tatu City: 44 MW in two 22 MW phases; ready for service Q1 2027
A15: S11 | B15: Nairametrics - Africa's data centre capacity exceeds 500 MW with 890 MW in pipeline (Fortren & Company) | C15: 2026-07-27 | D15: https://nairametrics.com/2026/07/27/africas-data-centre-capacity-exceeds-500-mw-with-890-mw-in-pipeline-report/ | E15: Africa >500 MW operational, 890 MW pipeline; South Africa >60% of operational capacity; Teraco Isando 70 MW; Lagos campus 36 MW
... A32: S27 | B32: TimesLive / MEA Tech Watch - Morocco to build 500MW renewable-powered data centre in Dakhla | C32: 2025-07-10 | D32: https://www.timeslive.co.za/news/africa/2025-07-10-morocco-to-build-data-centre-powered-by-renewable-energy/ | E32: Reported plan for a 500 MW renewable-powered data centre campus at Dakhla (headline-level; not independently verified)
A34: ID | B34: Conflict between sources | E34: How the model resolves it
A35: C1 | B35: Installed capacity: EPRA 3,192 MW (S5) vs 'about 3,000 MW' (S7) vs 'whole country has 2,300 MW' and 'peak crossed 3,000 MW' (S8) | E35: Model uses EPRA/Kenya Power series: peak demand 2,514 MW (Jun 2026) and reserve margin 3.34% (S2). The 2,300 MW and 3,000 MW remarks are political shorthand and are not used.
A36: C2 | B36: Nxtra Tatu City completion: 'this year' (S7) vs ready for service Q1 2027 (S10) | E36: Model uses Q1 2027 (S10) as the more specific, company-sourced date.
A37: C3 | B37: Ethiopia import uplift 'expected to double from December' (S2) with no year given | E37: Base case assumes December 2026 (available in 2027 annual peak); Stress case halves the uplift and delays it to 2028.
A38: C4 | B38: Peak-demand growth: official projection of c.5% a year (S2) vs observed 6.4% (FY25) and 8.5% (FY25 to Jun 2026) from S2 data | E38: Base case uses 6.5%; Favourable uses the official 5%; Stress uses 8%.
A39: C5 | B39: Large-user tariff KSh 7.99/kWh is from 2020 (S18); April 2026 pass-through charges add c.KSh 4.7/kWh (S16) | E39: Model treats the all-in tariff as a range ($0.065 favourable / $0.09 base / $0.11 stress) rather than quoting a single current rate.
A40: C6 | B40: Ruto's remark that one data centre needs 1,000 MW (S7, S8) is an upper-bound political statement about the full Microsoft/G42 campus | E40: Not used as a model input. Model sizes data-centre load from IT capacity, PUE and utilisation instead.

Sheet Checks
A1: Model integrity checks
A2: All checks should read TRUE.
A4: Check | B4: Result
A5: Base reserve margin reproduces the sourced 3.34% in 2026 | B5: =ABS(Grid!C30-Inputs!$E$7)<0.000001 -> TRUE
A6: Hub Targeted IT capacity in 2030 equals share x Africa 2030 capacity | B6: =ABS(Hub!G12-Inputs!$E$27*Inputs!$E$26)<0.000001 -> TRUE
A7: Hub Status quo adds no incremental grid load | B7: =Hub!G7=0 -> TRUE
A8: Campus NPV linear decomposition reproduces NPV | B8: =ABS(UnitEconomics!C43)<0.0001 -> TRUE
A9: Reserve margin matrix, Base supply / Status quo equals Grid reserve margin in 2030 | B9: =ABS(Matrix!C17-Grid!G30)<0.000001 -> TRUE
A10: Stress supply is never better than Base in 2030 (no hub) | B10: =Grid!G15<=Grid!G30 -> TRUE
A11: Base supply is never better than Favourable in 2030 (no hub) | B11: =Grid!G30<=Grid!G45 -> TRUE
A12: Tenant all-in cost equals sum of components (Base) | B12: =ABS(UnitEconomics!D8-UnitEconomics!D5-UnitEconomics!D6-UnitEconomics!D7)<0.000001 -> TRUE
A13: Screen weights sum to 100% | B13: =ABS(Screen!G5-1)<0.000001 -> TRUE
A14: Levers: package MW equals sum of lever rows | B14: =ABS(Levers!C10-SUM(Levers!C5:C9))<0.000001 -> TRUE
A16: All checks pass | B16: =AND(B5:B14) -> TRUE
